{"page":27,"page_size":200,"ads":[{"id":"ebda637ee7e9d7be","network":"taboola","advertiser":"Decoist","advertiser_slug":"decoist","title":"Hilarious Animals Sneak Up On Photographer","thumbnail":"/_img/taboola/ebda637ee7e9d7be","video_url":null,"countries":["AT","AU","BE","BG","BR","CH","CL","CZ","DE","DK","FI","FR","GB","GR","HU","IE","IL","IN","IT","JP","KR","MX","NL","NO","PL","QA","RO","SG","SK","TH","TR","TW","US","ZA"],"vertical":"general","ad_type":"text","days_active":16,"first_seen":"2026-04-15T18:53:40+00:00","last_seen":"2026-05-02T09:36:07+00:00"},{"id":"ef547dc2fa04b1d5","network":"taboola","advertiser":"knowledgeknower","advertiser_slug":"knowledgeknower","title":"Como comprar sistemas de som de estoque antigo","thumbnail":"/_img/taboola/ef547dc2fa04b1d5","video_url":null,"countries":["BR"],"vertical":"general","ad_type":"text","days_active":23,"first_seen":"2026-04-08T13:58:58+00:00","last_seen":"2026-05-02T09:20:20+00:00"},{"id":"f14c14f73861d934","network":"taboola","advertiser":"Mission Schilddruese","advertiser_slug":"mission-schilddruese","title":"L-Thyroxin wirkungslos? Das steckt wirklich dahinter","thumbnail":"/_img/taboola/f14c14f73861d934","video_url":null,"countries":["AT","CH","DE"],"vertical":"general","ad_type":"text","days_active":25,"first_seen":"2026-04-07T03:03:48+00:00","last_seen":"2026-05-02T09:06:28+00:00"},{"id":"fcf37ba8364ead84","network":"taboola","advertiser":"Ça m'intéresse","advertiser_slug":"a-m-int-resse","title":"Quelle est la durée de gestation de l’éléphant ?","thumbnail":"/_img/taboola/fcf37ba8364ead84","video_url":null,"countries":["FR"],"vertical":"general","ad_type":"video","days_active":11,"first_seen":"2026-04-20T10:40:30+00:00","last_seen":"2026-05-02T09:00:36+00:00"},{"id":"81b690877658167f","network":"taboola","advertiser":"Paperela","advertiser_slug":"paperela","title":"Jessica Alba, 44, Shows off Her Perfect Figure in A new photo","thumbnail":"/_img/taboola/81b690877658167f","video_url":null,"countries":["AU","BE","BG","CL","CZ","DK","FI","GR","HU","IE","KR","NO","NZ","QA","RO","SK","TR","TW","ZA"],"vertical":"general","ad_type":"photo","days_active":24,"first_seen":"2026-04-08T02:30:16+00:00","last_seen":"2026-05-02T09:00:05+00:00"},{"id":"eac71df4eb840eaa","network":"taboola","advertiser":"Mobilitätsanbieter","advertiser_slug":"mobilit-tsanbieter","title":"Das perfekte e-Bike finden: Top-Beratung & Probefahrt sichern","thumbnail":"/_img/taboola/eac71df4eb840eaa","video_url":null,"countries":["DE"],"vertical":"general","ad_type":"text","days_active":19,"first_seen":"2026-04-12T19:52:27+00:00","last_seen":"2026-05-02T08:58:43+00:00"},{"id":"0b5ebbb2e0aa28aa","network":"taboola","advertiser":"Graddi","advertiser_slug":"graddi","title":"Reinigen Sie fast alles mit diesem Hochdruck-Tool","thumbnail":"/_img/taboola/0b5ebbb2e0aa28aa","video_url":null,"countries":["DE"],"vertical":"general","ad_type":"text","days_active":12,"first_seen":"2026-04-19T14:22:08+00:00","last_seen":"2026-05-02T08:46:09+00:00"},{"id":"05b48d5cc32024f3","network":"taboola","advertiser":"EliteSearches | Dental Implants | Search Ads","advertiser_slug":"elitesearches-dental-implants-search-ads","title":"Dental Implants Cost For Seniors Over 70! (Take A Look)","thumbnail":"/_img/taboola/05b48d5cc32024f3","video_url":null,"countries":["US"],"vertical":"general","ad_type":"text","days_active":25,"first_seen":"2026-04-07T01:23:10+00:00","last_seen":"2026-05-02T08:01:03+00:00"},{"id":"25d6db3b04d38b8b","network":"taboola","advertiser":"nextflowwellness","advertiser_slug":"nextflowwellness","title":"The One Food Causing Your Memory Loss (And You Eat It Daily)","thumbnail":"/_img/taboola/25d6db3b04d38b8b","video_url":null,"countries":["US"],"vertical":"general","ad_type":"text","days_active":0,"first_seen":"2026-05-01T23:39:52+00:00","last_seen":"2026-05-02T07:51:00+00:00"},{"id":"0356af59dc503fe0","network":"taboola","advertiser":"Osteo Research","advertiser_slug":"osteo-research","title":"Top MD: This 1 Mineral Reduces Knee Pain \"Unlike Any other\"","thumbnail":"/_img/taboola/0356af59dc503fe0","video_url":null,"countries":["US"],"vertical":"general","ad_type":"text","days_active":10,"first_seen":"2026-04-22T02:21:51+00:00","last_seen":"2026-05-02T07:49:40+00:00"},{"id":"997a372209e0e844","network":"taboola","advertiser":"Wise Consumer Daily","advertiser_slug":"wise-consumer-daily","title":"Before and After: Stunning Breast Augmentation Transformations!","thumbnail":"/_img/taboola/997a372209e0e844","video_url":null,"countries":["US"],"vertical":"general","ad_type":"text","days_active":25,"first_seen":"2026-04-07T01:34:07+00:00","last_seen":"2026-05-02T07:47:48+00:00"},{"id":"f65d02450d647c39","network":"taboola","advertiser":"Decoist","advertiser_slug":"decoist","title":"40 Hardest Sports Records To Break, Ranked In Order","thumbnail":"/_img/taboola/f65d02450d647c39","video_url":null,"countries":["AT","AU","BE","BG","BR","CH","CL","CZ","DK","FI","FR","GB","GR","HU","IE","IN","IT","JP","KR","MX","NL","NO","PL","QA","RO","SG","SK","TH","TR","TW","ZA"],"vertical":"general","ad_type":"text","days_active":16,"first_seen":"2026-04-15T15:35:00+00:00","last_seen":"2026-05-02T07:39:58+00:00"},{"id":"2fbf19d82df5c2d9","network":"taboola","advertiser":"Konysbai","advertiser_slug":"konysbai","title":"Viеlе ältеre Меnsсhеn essеn Оrangеn und асhten niсht dаrauf","thumbnail":"/_img/taboola/2fbf19d82df5c2d9","video_url":null,"countries":["DE"],"vertical":"general","ad_type":"text","days_active":20,"first_seen":"2026-04-12T01:07:24+00:00","last_seen":"2026-05-02T07:29:08+00:00"},{"id":"4b81b2c05795fab9","network":"taboola","advertiser":"Granny Pod Trends","advertiser_slug":"granny-pod-trends","title":"Why Everyone Is Talking About Granny Pods in 2026","thumbnail":"/_img/taboola/4b81b2c05795fab9","video_url":null,"countries":["AU","CA","GB","IE","NZ"],"vertical":"general","ad_type":"text","days_active":24,"first_seen":"2026-04-07T14:29:18+00:00","last_seen":"2026-05-02T07:20:36+00:00"},{"id":"6530e3c5ca675ab2","network":"taboola","advertiser":"GlowGeheimnis","advertiser_slug":"glowgeheimnis","title":"Der #1 Mascara-Fehler bei 50-jährigen (1+1 GRATIS)","thumbnail":"/_img/taboola/6530e3c5ca675ab2","video_url":null,"countries":["DE"],"vertical":"auto","ad_type":"text","days_active":20,"first_seen":"2026-04-12T06:19:18+00:00","last_seen":"2026-05-02T07:15:20+00:00"},{"id":"130a0fcbe77d3dd4","network":"taboola","advertiser":"Gaming PC","advertiser_slug":"gaming-pc","title":"Key Factors To Consider When Choosing A Gaming PC","thumbnail":"/_img/taboola/130a0fcbe77d3dd4","video_url":null,"countries":["AU","BE","BR","CL","CZ","FI","GB","IE","IT","JP","MX","NL","SG","TH","US"],"vertical":"general","ad_type":"text","days_active":7,"first_seen":"2026-04-24T21:50:11+00:00","last_seen":"2026-05-02T07:08:04+00:00"},{"id":"3ac926565c27e064","network":"taboola","advertiser":"Tips And Life Hacks","advertiser_slug":"tips-and-life-hacks","title":"She Put Fabric Softener in Her Vacuum – What Happened Surprised Everyone!","thumbnail":"/_img/taboola/3ac926565c27e064","video_url":null,"countries":["AU","BE","BG","BR","CA","CL","CZ","FI","FR","GR","HU","IE","KR","NZ","QA","RO","SK","TH","TR","TW","US","ZA"],"vertical":"general","ad_type":"photo","days_active":25,"first_seen":"2026-04-07T01:34:54+00:00","last_seen":"2026-05-02T06:22:28+00:00"},{"id":"815c313b8faf0749","network":"taboola","advertiser":"Trading Blvd","advertiser_slug":"trading-blvd","title":"손흥민의 재산은 당신을 말문이 막히게 할 것입니다","thumbnail":"/_img/taboola/815c313b8faf0749","video_url":null,"countries":["KR"],"vertical":"general","ad_type":"photo","days_active":18,"first_seen":"2026-04-13T17:27:29+00:00","last_seen":"2026-05-02T05:53:56+00:00"},{"id":"7e9536a92373d38b","network":"taboola","advertiser":"MINI","advertiser_slug":"mini","title":"Elige tu oferta de mantenimiento y que nada te pare.","thumbnail":"/_img/taboola/7e9536a92373d38b","video_url":null,"countries":["ES"],"vertical":"general","ad_type":"text","days_active":15,"first_seen":"2026-04-16T10:08:59+00:00","last_seen":"2026-05-02T05:41:20+00:00"},{"id":"186176505de9b343","network":"taboola","advertiser":"Allianz Auto","advertiser_slug":"allianz-auto","title":"Contrats Auto au kilomètre : 3 formules dès 22€/mois* (Trouvez la vôtre !)","thumbnail":"/_img/taboola/186176505de9b343","video_url":null,"countries":["FR"],"vertical":"general","ad_type":"text","days_active":25,"first_seen":"2026-04-07T01:40:41+00:00","last_seen":"2026-05-02T05:10:09+00:00"},{"id":"113dd077eb85fa2e","network":"taboola","advertiser":"onestoparticle.com","advertiser_slug":"onestoparticle-com","title":"Take Online Courses from Home - Free","thumbnail":"/_img/taboola/113dd077eb85fa2e","video_url":null,"countries":["AT","AU","DE","FR","GB"],"vertical":"general","ad_type":"text","days_active":12,"first_seen":"2026-04-19T14:29:37+00:00","last_seen":"2026-05-02T04:46:59+00:00"},{"id":"2f46a7703363c77e","network":"taboola","advertiser":"Sherlock","advertiser_slug":"sherlock","title":"Find the hidden objects - most fail the last one","thumbnail":"/_img/taboola/2f46a7703363c77e","video_url":null,"countries":["US"],"vertical":"general","ad_type":"text","days_active":19,"first_seen":"2026-04-12T08:38:06+00:00","last_seen":"2026-05-02T04:39:06+00:00"},{"id":"b5f57ea687a29776","network":"taboola","advertiser":"MINI","advertiser_slug":"mini","title":"Personnalisez votre MINI COUNTRYMAN.","thumbnail":"/_img/taboola/b5f57ea687a29776","video_url":null,"countries":["FR"],"vertical":"general","ad_type":"text","days_active":25,"first_seen":"2026-04-07T02:02:32+00:00","last_seen":"2026-05-02T04:28:57+00:00"},{"id":"bb5a712fc3b0adf0","network":"taboola","advertiser":"Rubaxx CBD Plus","advertiser_slug":"rubaxx-cbd-plus","title":"NEUES Gel mit über 1000mg CBD aktiviert die Haut und entspannt beanspruchte Muskeln","thumbnail":"/_img/taboola/bb5a712fc3b0adf0","video_url":null,"countries":["DE"],"vertical":"health","ad_type":"text","days_active":17,"first_seen":"2026-04-14T22:27:25+00:00","last_seen":"2026-05-02T04:17:08+00:00"},{"id":"b292c8409e81bcf3","network":"taboola","advertiser":"Lifehack.reviews","advertiser_slug":"lifehack-reviews","title":"What Happens When You Pour Citric Acid in Drain","thumbnail":"/_img/taboola/b292c8409e81bcf3","video_url":null,"countries":["US"],"vertical":"general","ad_type":"text","days_active":10,"first_seen":"2026-04-21T14:29:11+00:00","last_seen":"2026-05-02T03:54:12+00:00"},{"id":"06318bf3225c8e4e","network":"taboola","advertiser":"pet toy","advertiser_slug":"pet-toy","title":"The Toy That Tires Out My Dog Without Me Throwing A Ball","thumbnail":"/_img/taboola/06318bf3225c8e4e","video_url":null,"countries":["US"],"vertical":"general","ad_type":"text","days_active":6,"first_seen":"2026-04-25T08:56:52+00:00","last_seen":"2026-05-02T03:17:12+00:00"},{"id":"419ca7e42f94b57c","network":"taboola","advertiser":"Welt der Gesundheit","advertiser_slug":"welt-der-gesundheit","title":"Arthrose? Dieser Tipp macht Sie in Rekordzeit wieder mobil!","thumbnail":"/_img/taboola/419ca7e42f94b57c","video_url":null,"countries":["DE"],"vertical":"general","ad_type":"text","days_active":11,"first_seen":"2026-04-20T10:28:24+00:00","last_seen":"2026-05-02T03:00:37+00:00"},{"id":"8f90403f3defa2fe","network":"taboola","advertiser":"The Skincare Magazine","advertiser_slug":"the-skincare-magazine","title":"Dermatologists Agree: This Drugstore Gem Is All You Need for Tighter Skin","thumbnail":"/_img/taboola/8f90403f3defa2fe","video_url":null,"countries":["US"],"vertical":"health","ad_type":"text","days_active":9,"first_seen":"2026-04-22T02:59:23+00:00","last_seen":"2026-05-02T02:41:39+00:00"},{"id":"e158d9a88488793c","network":"taboola","advertiser":"Lifehack.reviews","advertiser_slug":"lifehack-reviews","title":"This Mouthwash Toilet Trick Is Going Viral Now","thumbnail":"/_img/taboola/e158d9a88488793c","video_url":null,"countries":["US"],"vertical":"general","ad_type":"text","days_active":10,"first_seen":"2026-04-21T11:27:06+00:00","last_seen":"2026-05-02T02:34:15+00:00"},{"id":"4194ea90fd1d25a6","network":"taboola","advertiser":"onestoparticle.com","advertiser_slug":"onestoparticle-com","title":"If You Speak English, You Might be Eligible for Free Online MBA Courses in USA","thumbnail":"/_img/taboola/4194ea90fd1d25a6","video_url":null,"countries":["BE","DK","ES","FI","FR","GR","IE","IL","IN","IT","JP","NO","QA","SG","ZA"],"vertical":"general","ad_type":"text","days_active":17,"first_seen":"2026-04-14T16:59:59+00:00","last_seen":"2026-05-02T02:16:53+00:00"},{"id":"55741e6dce8ce0af","network":"taboola","advertiser":"Máquina Industrial","advertiser_slug":"m-quina-industrial","title":"Vantagens da perfuração com trado contínuo","thumbnail":"/_img/taboola/55741e6dce8ce0af","video_url":null,"countries":["BR"],"vertical":"general","ad_type":"text","days_active":24,"first_seen":"2026-04-07T05:00:05+00:00","last_seen":"2026-05-02T02:09:53+00:00"},{"id":"62edd5e6cd59921e","network":"taboola","advertiser":"Walkergrey","advertiser_slug":"walkergrey","title":"Ultra-Soft Linen Shirt Loved by Thousands of Men","thumbnail":"/_img/taboola/62edd5e6cd59921e","video_url":null,"countries":["US"],"vertical":"general","ad_type":"text","days_active":9,"first_seen":"2026-04-22T22:36:15+00:00","last_seen":"2026-05-02T01:53:00+00:00"},{"id":"cf495f075c379476","network":"taboola","advertiser":"Daily Quiz Dose","advertiser_slug":"daily-quiz-dose","title":"Your Fate Is One Spin Away","thumbnail":"/_img/taboola/cf495f075c379476","video_url":null,"countries":["BE","BG","BR","CL","CZ","DK","GR","HU","IN","KR","MX","NO","NZ","QA","RO","SK","TR","TW","ZA"],"vertical":"general","ad_type":"video","days_active":24,"first_seen":"2026-04-07T19:01:52+00:00","last_seen":"2026-05-02T01:11:37+00:00"},{"id":"dd94c18530006943","network":"taboola","advertiser":"Town and Country","advertiser_slug":"town-and-country","title":"In Photos: Vintage Snaps of Celebrities On Set","thumbnail":"/_img/taboola/dd94c18530006943","video_url":null,"countries":["US"],"vertical":"general","ad_type":"text","days_active":25,"first_seen":"2026-04-07T00:00:51+00:00","last_seen":"2026-05-02T00:53:35+00:00"},{"id":"0a50a19fa289248a","network":"taboola","advertiser":"Telekom","advertiser_slug":"telekom","title":"Testsieger-Tarif: MagentaTV MegaStream","thumbnail":"/_img/taboola/0a50a19fa289248a","video_url":null,"countries":["DE"],"vertical":"general","ad_type":"text","days_active":10,"first_seen":"2026-04-21T18:33:05+00:00","last_seen":"2026-05-02T00:49:58+00:00"},{"id":"c3b0a0d28694f5d0","network":"taboola","advertiser":"Town and Country","advertiser_slug":"town-and-country","title":"44 Best Vintage Celebrity On-Set Photos","thumbnail":"/_img/taboola/c3b0a0d28694f5d0","video_url":null,"countries":["US"],"vertical":"general","ad_type":"text","days_active":19,"first_seen":"2026-04-12T17:10:15+00:00","last_seen":"2026-05-02T00:37:17+00:00"},{"id":"d462dae19dabb0e7","network":"taboola","advertiser":"12facts.com","advertiser_slug":"12facts-com","title":"Top 30 Der Schönsten Frauen Der Welt – Stimmen Sie Zu?","thumbnail":"/_img/taboola/d462dae19dabb0e7","video_url":null,"countries":["DE"],"vertical":"general","ad_type":"text","days_active":19,"first_seen":"2026-04-12T05:26:19+00:00","last_seen":"2026-05-02T00:06:39+00:00"},{"id":"3e7f90ac73110630","network":"taboola","advertiser":"Feeder","advertiser_slug":"feeder","title":"Why 30,000 Bird Lovers Are Swapping Their Feeders This Season","thumbnail":"/_img/taboola/3e7f90ac73110630","video_url":null,"countries":["US"],"vertical":"general","ad_type":"text","days_active":1,"first_seen":"2026-04-30T06:36:11+00:00","last_seen":"2026-05-01T23:53:10+00:00"},{"id":"9ac76ab873077f92","network":"taboola","advertiser":"faltenreduzieren.com","advertiser_slug":"faltenreduzieren-com","title":"Kreppige Haut? Kollagen ist nicht das Problem, sondern dies","thumbnail":"/_img/taboola/9ac76ab873077f92","video_url":null,"countries":["DE"],"vertical":"general","ad_type":"text","days_active":20,"first_seen":"2026-04-11T23:07:58+00:00","last_seen":"2026-05-01T23:44:24+00:00"},{"id":"ef77b850e385fe4f","network":"taboola","advertiser":"Brenna Marie","advertiser_slug":"brenna-marie","title":"Viele Rentner wissen noch nichts von den Änderungen 2026","thumbnail":"/_img/taboola/ef77b850e385fe4f","video_url":null,"countries":["DE"],"vertical":"general","ad_type":"text","days_active":3,"first_seen":"2026-04-28T19:52:08+00:00","last_seen":"2026-05-01T23:40:57+00:00"},{"id":"f910d1222ccd6c16","network":"taboola","advertiser":"thebearloan.com","advertiser_slug":"thebearloan-com","title":"Explore personal loan offers designed for different credit profiles.","thumbnail":"/_img/taboola/f910d1222ccd6c16","video_url":null,"countries":["US"],"vertical":"finance","ad_type":"text","days_active":4,"first_seen":"2026-04-27T15:06:08+00:00","last_seen":"2026-05-01T23:38:20+00:00"},{"id":"400e294eee9cc68a","network":"taboola","advertiser":"Thyroid-world","advertiser_slug":"thyroid-world","title":"Is Your Levothyroxine Making Your Hypothyroidism Worse?","thumbnail":"/_img/taboola/400e294eee9cc68a","video_url":null,"countries":["US"],"vertical":"general","ad_type":"text","days_active":20,"first_seen":"2026-04-11T12:28:13+00:00","last_seen":"2026-05-01T23:38:14+00:00"},{"id":"23eb25669eacc391","network":"taboola","advertiser":"onestoparticle.com","advertiser_slug":"onestoparticle-com","title":"Take Online Courses from Home - Free","thumbnail":"/_img/taboola/23eb25669eacc391","video_url":null,"countries":["AT","AU","BG","CZ","DE","DK","FI","FR","GB","GR","HU","RO"],"vertical":"general","ad_type":"text","days_active":24,"first_seen":"2026-04-07T00:36:23+00:00","last_seen":"2026-05-01T23:14:18+00:00"},{"id":"9adaff7045cd8d0e","network":"taboola","advertiser":"Decoist","advertiser_slug":"decoist","title":"21 Planes So Bad They Never Should’ve Left The Ground…","thumbnail":"/_img/taboola/9adaff7045cd8d0e","video_url":null,"countries":["BE","BG","BR","CL","FI","FR","GR","HU","IE","IN","JP","KR","MX","NL","NO","PL","QA","RO","SG","SK","TR","TW","ZA"],"vertical":"general","ad_type":"text","days_active":16,"first_seen":"2026-04-15T11:29:43+00:00","last_seen":"2026-05-01T23:00:56+00:00"},{"id":"e1a18cf0ab532fad","network":"taboola","advertiser":"NewsHub","advertiser_slug":"newshub","title":"Understanding Scratch and Dent Lawn Mower Prices: A Guide","thumbnail":"/_img/taboola/e1a18cf0ab532fad","video_url":null,"countries":["AU","BE","BG","CA","CH","CL","DK","FI","FR","NL","NO","QA","RO","TR","US","ZA"],"vertical":"general","ad_type":"text","days_active":6,"first_seen":"2026-04-25T05:53:44+00:00","last_seen":"2026-05-01T22:59:14+00:00"},{"id":"66c7be58f8d8549d","network":"taboola","advertiser":"nutrition-science.de","advertiser_slug":"nutrition-science-de","title":"Das finden Frauen attraktiv bei Männern Ü40 (Testosteron)","thumbnail":"/_img/taboola/66c7be58f8d8549d","video_url":null,"countries":["DE"],"vertical":"general","ad_type":"text","days_active":20,"first_seen":"2026-04-11T22:22:27+00:00","last_seen":"2026-05-01T22:58:12+00:00"},{"id":"6cc89249286d4b39","network":"taboola","advertiser":"Coussin d'Assise Ergonomique","advertiser_slug":"coussin-d-assise-ergonomique","title":"S'asseoir avec confort : En quelques mois, ce coussin est devenu l'indispensable des seniors","thumbnail":"/_img/taboola/6cc89249286d4b39","video_url":null,"countries":["FR"],"vertical":"general","ad_type":"text","days_active":24,"first_seen":"2026-04-07T02:02:38+00:00","last_seen":"2026-05-01T22:17:20+00:00"},{"id":"9a0d1a97d73c152d","network":"taboola","advertiser":"reinergesundheitsschub.de","advertiser_slug":"reinergesundheitsschub-de","title":"Ein Kardiologe sagt: „Das ist wie eine Hochdruckreinigung für Ihre Leber\"","thumbnail":"/_img/taboola/9a0d1a97d73c152d","video_url":null,"countries":["DE"],"vertical":"general","ad_type":"text","days_active":18,"first_seen":"2026-04-13T07:45:54+00:00","last_seen":"2026-05-01T22:02:02+00:00"},{"id":"4e4f3667bcd7215a","network":"taboola","advertiser":"Cessione del Quinto","advertiser_slug":"cessione-del-quinto","title":"Cessione del Quinto INPS 2026: da 5.000€ a 75.000€+ con rate costanti! Scopri come richiederla!","thumbnail":"/_img/taboola/4e4f3667bcd7215a","video_url":null,"countries":["IT"],"vertical":"general","ad_type":"text","days_active":14,"first_seen":"2026-04-17T10:32:20+00:00","last_seen":"2026-05-01T21:57:29+00:00"},{"id":"9baa9a693b9e7c3c","network":"taboola","advertiser":"Toyota Prado","advertiser_slug":"toyota-prado","title":"2026 Toyota Prado Prices May Surprise Buyers Right Now","thumbnail":"/_img/taboola/9baa9a693b9e7c3c","video_url":null,"countries":["AT","AU","BE","BR","CL","CZ","ES","FI","IE","IT","JP","MX","NL","SG","SK","TH"],"vertical":"auto","ad_type":"text","days_active":3,"first_seen":"2026-04-28T09:57:01+00:00","last_seen":"2026-05-01T21:47:53+00:00"},{"id":"4ce2171a25f2f97a","network":"taboola","advertiser":"taplive.online","advertiser_slug":"taplive-online","title":"Ruhige Hunderassen für kleine Wohnräume","thumbnail":"/_img/taboola/4ce2171a25f2f97a","video_url":null,"countries":["DE"],"vertical":"general","ad_type":"text","days_active":20,"first_seen":"2026-04-11T20:09:40+00:00","last_seen":"2026-05-01T20:37:07+00:00"},{"id":"3891a2310e7a9fb7","network":"taboola","advertiser":"trendmaze.page","advertiser_slug":"trendmaze-page","title":"Los signos con más energía y liderazgo","thumbnail":"/_img/taboola/3891a2310e7a9fb7","video_url":null,"countries":["ES"],"vertical":"general","ad_type":"photo","days_active":19,"first_seen":"2026-04-12T13:21:43+00:00","last_seen":"2026-05-01T20:07:06+00:00"},{"id":"696c05b4eacaa113","network":"taboola","advertiser":"TEMU","advertiser_slug":"temu","title":"Temu Clearance Sale","thumbnail":"/_img/taboola/696c05b4eacaa113","video_url":null,"countries":["US"],"vertical":"general","ad_type":"text","days_active":18,"first_seen":"2026-04-13T03:18:54+00:00","last_seen":"2026-05-01T19:46:17+00:00"},{"id":"ca11896a26855e32","network":"taboola","advertiser":"TEMU","advertiser_slug":"temu","title":"Temu Clearance Sale","thumbnail":"/_img/taboola/ca11896a26855e32","video_url":null,"countries":["US"],"vertical":"general","ad_type":"text","days_active":7,"first_seen":"2026-04-24T10:38:36+00:00","last_seen":"2026-05-01T19:45:22+00:00"},{"id":"191e39d3868d232f","network":"taboola","advertiser":"Instant Water Leak Sealant | Search Ads","advertiser_slug":"instant-water-leak-sealant-search-ads","title":"Instant Water Leak Repair","thumbnail":"/_img/taboola/191e39d3868d232f","video_url":null,"countries":["AT","AU","BE","CH","CZ","DE","DK","ES","FI","FR","GB","GR","IE","IN","IT","JP","KR","MX","NL","NO","QA","RO","TR","TW","ZA"],"vertical":"general","ad_type":"text","days_active":11,"first_seen":"2026-04-20T13:02:52+00:00","last_seen":"2026-05-01T19:05:22+00:00"},{"id":"d03c0e68d3920aa6","network":"taboola","advertiser":"onestoparticle.com","advertiser_slug":"onestoparticle-com","title":"Specialized Training, Degrees, Certifications & More.","thumbnail":"/_img/taboola/d03c0e68d3920aa6","video_url":null,"countries":["AT","AU","BE","BR","CZ","DE","FI","FR","GB","GR","PT","SK","TR","US"],"vertical":"general","ad_type":"text","days_active":24,"first_seen":"2026-04-07T06:24:11+00:00","last_seen":"2026-05-01T18:15:25+00:00"},{"id":"8787ff8f3b95d1ff","network":"taboola","advertiser":"Carglass","advertiser_slug":"carglass","title":"Caja de Herramientas Casals de Regalo","thumbnail":"/_img/taboola/8787ff8f3b95d1ff","video_url":null,"countries":["ES"],"vertical":"auto","ad_type":"text","days_active":19,"first_seen":"2026-04-12T10:47:06+00:00","last_seen":"2026-05-01T17:40:14+00:00"},{"id":"54905ad240656c0d","network":"taboola","advertiser":"Mister Market Pro","advertiser_slug":"mister-market-pro","title":"Er is een gratis financieel opleidingsprogramma gestart in Nederland","thumbnail":"/_img/taboola/54905ad240656c0d","video_url":null,"countries":["NL"],"vertical":"general","ad_type":"text","days_active":19,"first_seen":"2026-04-11T18:36:11+00:00","last_seen":"2026-05-01T17:37:24+00:00"},{"id":"e8ecaaffae7160ef","network":"taboola","advertiser":"Fetchapro","advertiser_slug":"fetchapro","title":"Council Bluffs Seniors Are Getting Bathroom Upgrades If They Live In These Zip Codes","thumbnail":"/_img/taboola/e8ecaaffae7160ef","video_url":null,"countries":["US"],"vertical":"home","ad_type":"text","days_active":6,"first_seen":"2026-04-25T12:39:47+00:00","last_seen":"2026-05-01T17:22:18+00:00"},{"id":"e70940c4b319f91d","network":"taboola","advertiser":"Fisher Investments","advertiser_slug":"fisher-investments","title":"Was ist der größte Fehler, den Anleger mit 500.000 € begehen?","thumbnail":"/_img/taboola/e70940c4b319f91d","video_url":null,"countries":["DE"],"vertical":"finance","ad_type":"text","days_active":4,"first_seen":"2026-04-27T13:40:32+00:00","last_seen":"2026-05-01T17:20:09+00:00"},{"id":"d0aaafea2501b65f","network":"taboola","advertiser":"Araç Değeri | Arama Reklamları","advertiser_slug":"ara-de-eri-arama-reklamlar","title":"Arabanızın 2026'daki Gerçek Değeri Ne Kadar?","thumbnail":"/_img/taboola/d0aaafea2501b65f","video_url":null,"countries":["TR"],"vertical":"general","ad_type":"text","days_active":24,"first_seen":"2026-04-07T01:35:48+00:00","last_seen":"2026-05-01T16:45:25+00:00"},{"id":"f2345185021b4fbb","network":"taboola","advertiser":"Trading Blvd","advertiser_slug":"trading-blvd","title":"Lindsay Lohan, 39, Owns One of the Most Expensive Cars in the World","thumbnail":"/_img/taboola/f2345185021b4fbb","video_url":null,"countries":["AU","BE","BG","BR","CA","CL","CZ","DK","ES","FI","GR","HU","IE","KR","MX","NL","NO","NZ","PL","PT","QA","RO","SE","SK","TR","TW","US","ZA"],"vertical":"auto","ad_type":"text","days_active":24,"first_seen":"2026-04-07T09:31:55+00:00","last_seen":"2026-05-01T16:44:21+00:00"},{"id":"2f704be88c474d43","network":"taboola","advertiser":"Unfaility.com","advertiser_slug":"unfaility-com","title":"Do You Remember Her? Take A Deep Breath Before Looking At Her Now.","thumbnail":"/_img/taboola/2f704be88c474d43","video_url":null,"countries":["BE","FR","GB","US"],"vertical":"general","ad_type":"photo","days_active":22,"first_seen":"2026-04-09T04:15:34+00:00","last_seen":"2026-05-01T16:24:33+00:00"},{"id":"a18931e563e20a29","network":"taboola","advertiser":"Lingxi Games","advertiser_slug":"lingxi-games","title":"Master Three Kingdoms War","thumbnail":"/_img/taboola/a18931e563e20a29","video_url":null,"countries":["AT","BE","CZ","DK","ES","FI","FR","GR","HU","IE","IT","NL","SG","TW"],"vertical":"general","ad_type":"text","days_active":10,"first_seen":"2026-04-20T19:11:53+00:00","last_seen":"2026-05-01T16:13:06+00:00"},{"id":"74c7a7a1132376f0","network":"taboola","advertiser":"Lingxi Games","advertiser_slug":"lingxi-games","title":"Strategy Meets History","thumbnail":"/_img/taboola/74c7a7a1132376f0","video_url":null,"countries":["BE","CZ","DK","ES","FI","FR","GR","HU","IE","NL","SG","TW"],"vertical":"general","ad_type":"text","days_active":10,"first_seen":"2026-04-20T21:22:13+00:00","last_seen":"2026-05-01T16:10:11+00:00"},{"id":"2a66268c853291fd","network":"taboola","advertiser":"Gesundheitsmagazin","advertiser_slug":"gesundheitsmagazin","title":"Natürlich durch die Wechseljahre: Diese hormonfreie Methode hilft wirklich!","thumbnail":"/_img/taboola/2a66268c853291fd","video_url":null,"countries":["DE"],"vertical":"general","ad_type":"text","days_active":1,"first_seen":"2026-04-30T09:27:58+00:00","last_seen":"2026-05-01T16:04:12+00:00"},{"id":"baf1cd9e557b2430","network":"taboola","advertiser":"Lingxi Games","advertiser_slug":"lingxi-games","title":"Global Strategy Game Hit","thumbnail":"/_img/taboola/baf1cd9e557b2430","video_url":null,"countries":["AT","BE","BG","CZ","DK","ES","FI","FR","GR","HU","IE","IT","NL","RO","SG","TW"],"vertical":"general","ad_type":"text","days_active":10,"first_seen":"2026-04-20T18:30:14+00:00","last_seen":"2026-05-01T16:02:36+00:00"},{"id":"e7c487c1511fac45","network":"taboola","advertiser":"TopGentlemen.com","advertiser_slug":"topgentlemen-com","title":"18 Celebrities Who Converted To Islam","thumbnail":"/_img/taboola/e7c487c1511fac45","video_url":null,"countries":["AU","BE","CZ","DK","FI","GB","GR","HU","IE","IT","JP","NL","NO","NZ","PL","RO","SG","SK"],"vertical":"general","ad_type":"photo","days_active":24,"first_seen":"2026-04-07T07:41:48+00:00","last_seen":"2026-05-01T15:49:58+00:00"},{"id":"d477b6062763ed91","network":"taboola","advertiser":"Topgentlemen.com","advertiser_slug":"topgentlemen-com","title":"Top 20 Most Dangerous Dog Breeds You Should Beware of","thumbnail":"/_img/taboola/d477b6062763ed91","video_url":null,"countries":["AU","BE","CZ","DK","ES","FI","FR","GB","GR","HU","IE","IL","IT","JP","NL","NO","PL","SK"],"vertical":"general","ad_type":"photo","days_active":13,"first_seen":"2026-04-17T20:25:04+00:00","last_seen":"2026-05-01T15:37:59+00:00"},{"id":"1dfd1b89717091cd","network":"taboola","advertiser":"Cordelia Cruises","advertiser_slug":"cordelia-cruises","title":"Malé & Colombo Cruise – Up to 26% Off","thumbnail":"/_img/taboola/1dfd1b89717091cd","video_url":null,"countries":["IN"],"vertical":"travel","ad_type":"text","days_active":17,"first_seen":"2026-04-13T20:46:33+00:00","last_seen":"2026-05-01T15:37:13+00:00"},{"id":"e4d1e93685a0dfa3","network":"taboola","advertiser":"Lendio","advertiser_slug":"lendio","title":"Don't wait for business financing. Apply once to over 75 lenders and funding partners.","thumbnail":"/_img/taboola/e4d1e93685a0dfa3","video_url":null,"countries":["US"],"vertical":"general","ad_type":"text","days_active":21,"first_seen":"2026-04-10T05:03:40+00:00","last_seen":"2026-05-01T15:35:29+00:00"},{"id":"adc5427180771999","network":"taboola","advertiser":"BuzzNFun.com","advertiser_slug":"buzznfun-com","title":"Stuning Vintage Photos Of Most Beautiful Female Icons","thumbnail":"/_img/taboola/adc5427180771999","video_url":null,"countries":["BE","BG","BR","CL","CZ","GB","GR","HU","IE","IL","IN","KR","MX","NO","PL","QA","RO","SK","TR","TW","ZA"],"vertical":"general","ad_type":"photo","days_active":14,"first_seen":"2026-04-17T12:47:09+00:00","last_seen":"2026-05-01T15:23:56+00:00"},{"id":"9d7a54a807c6c2cc","network":"taboola","advertiser":"TopGentlemen.com","advertiser_slug":"topgentlemen-com","title":"إذا رأيت هذه الحشرة البنية في فناء المنزل، فيجب عليك اتخاذ إجراء على الفور","thumbnail":"/_img/taboola/9d7a54a807c6c2cc","video_url":null,"countries":["QA"],"vertical":"general","ad_type":"text","days_active":14,"first_seen":"2026-04-17T11:40:20+00:00","last_seen":"2026-05-01T15:23:11+00:00"},{"id":"a7bb724fd0cf0ccf","network":"taboola","advertiser":"BuzzNFun.com","advertiser_slug":"buzznfun-com","title":"Vintage Photos Of Most Beautiful Female Icons","thumbnail":"/_img/taboola/a7bb724fd0cf0ccf","video_url":null,"countries":["BE","BG","BR","CL","CZ","GR","HU","IN","KR","MX","PL","QA","RO","SK","TH","TR","TW","ZA"],"vertical":"general","ad_type":"photo","days_active":14,"first_seen":"2026-04-17T11:21:59+00:00","last_seen":"2026-05-01T15:13:48+00:00"},{"id":"4c8ef14bf298a8ff","network":"taboola","advertiser":"TopGentlemen.com","advertiser_slug":"topgentlemen-com","title":"18 celebrities who embraced Islam – you’ll be surprised by some","thumbnail":"/_img/taboola/4c8ef14bf298a8ff","video_url":null,"countries":["BE","CZ","DK","ES","FI","FR","GB","GR","HU","IE","IT","NL","NO","NZ","PL","SK"],"vertical":"general","ad_type":"photo","days_active":24,"first_seen":"2026-04-07T02:45:25+00:00","last_seen":"2026-05-01T15:13:17+00:00"},{"id":"ad9fba9741b78fb8","network":"taboola","advertiser":"NewsHub","advertiser_slug":"newshub","title":"Learn more about smart inventory","thumbnail":"/_img/taboola/ad9fba9741b78fb8","video_url":null,"countries":["AU","BE","BG","BR","CL","DK","FR","GB","GR","IE","KR","MX","PL","QA","RO","SK","TR","ZA"],"vertical":"general","ad_type":"text","days_active":9,"first_seen":"2026-04-22T00:52:27+00:00","last_seen":"2026-05-01T15:11:38+00:00"},{"id":"8cdfda1fa720d247","network":"taboola","advertiser":"PureTopics | Search Ads","advertiser_slug":"puretopics-search-ads","title":"Research Small Ship Cruise Lines","thumbnail":"/_img/taboola/8cdfda1fa720d247","video_url":null,"countries":["US"],"vertical":"travel","ad_type":"text","days_active":20,"first_seen":"2026-04-10T18:40:03+00:00","last_seen":"2026-05-01T15:01:15+00:00"},{"id":"fe8804bbc812a312","network":"taboola","advertiser":"NewsHub","advertiser_slug":"newshub","title":"Luxury Private Rides","thumbnail":"/_img/taboola/fe8804bbc812a312","video_url":null,"countries":["AU","BE","BG","CL","FR","GB","GR","KR","PL","QA","RO","SK","TR","ZA"],"vertical":"general","ad_type":"text","days_active":8,"first_seen":"2026-04-23T09:42:43+00:00","last_seen":"2026-05-01T14:51:13+00:00"},{"id":"074810e4cd9e054f","network":"taboola","advertiser":"Tendencias de Belleza","advertiser_slug":"tendencias-de-belleza","title":"Cómo corregir el rostro caído sin bótox ni agujas (tarda 7 segundos)","thumbnail":"/_img/taboola/074810e4cd9e054f","video_url":null,"countries":["ES"],"vertical":"general","ad_type":"text","days_active":19,"first_seen":"2026-04-12T08:55:54+00:00","last_seen":"2026-05-01T14:44:33+00:00"},{"id":"7e7f6d5ec63ae634","network":"taboola","advertiser":"BuzzNFun.com","advertiser_slug":"buzznfun-com","title":"Vintage Photos Of Most Beautiful Female Icons","thumbnail":"/_img/taboola/7e7f6d5ec63ae634","video_url":null,"countries":["BE","BG","BR","CL","FI","GR","HU","IE","IN","KR","MX","NL","PL","QA","RO","TR","TW","ZA"],"vertical":"general","ad_type":"photo","days_active":14,"first_seen":"2026-04-17T11:29:21+00:00","last_seen":"2026-05-01T14:34:12+00:00"},{"id":"c1986d43b2fb8742","network":"taboola","advertiser":"Sandbanks Observer","advertiser_slug":"sandbanks-observer","title":"Coordinated Action Conducted Across 15 High-End Sandbanks Properties","thumbnail":"/_img/taboola/c1986d43b2fb8742","video_url":null,"countries":["GB"],"vertical":"finance","ad_type":"text","days_active":21,"first_seen":"2026-04-09T16:43:06+00:00","last_seen":"2026-05-01T14:28:29+00:00"},{"id":"95bf499c2bc27b58","network":"taboola","advertiser":"AmericanHealth Report","advertiser_slug":"americanhealth-report","title":"Finally Shoes That Truly Help Older Adults","thumbnail":"/_img/taboola/95bf499c2bc27b58","video_url":null,"countries":["US"],"vertical":"general","ad_type":"text","days_active":10,"first_seen":"2026-04-21T06:08:31+00:00","last_seen":"2026-05-01T14:21:02+00:00"},{"id":"d36f96cdcc399c70","network":"taboola","advertiser":"cosmetica","advertiser_slug":"cosmetica","title":"Nisan Fırsatlarıyla Işıldayın","thumbnail":"/_img/taboola/d36f96cdcc399c70","video_url":null,"countries":["TR"],"vertical":"general","ad_type":"text","days_active":23,"first_seen":"2026-04-07T19:37:12+00:00","last_seen":"2026-05-01T14:08:48+00:00"},{"id":"d0fea8d54e5b595a","network":"taboola","advertiser":"Gencallar","advertiser_slug":"gencallar","title":"title_-1498049055745453978","thumbnail":"/_img/taboola/d0fea8d54e5b595a","video_url":null,"countries":["TR"],"vertical":"general","ad_type":"text","days_active":8,"first_seen":"2026-04-22T17:26:16+00:00","last_seen":"2026-05-01T14:08:32+00:00"},{"id":"c36c19760121eb9f","network":"taboola","advertiser":"Alpaca","advertiser_slug":"alpaca","title":"Jeden Tag diese Schuhe – plötzlich war der Bauch weg","thumbnail":"/_img/taboola/c36c19760121eb9f","video_url":null,"countries":["DE"],"vertical":"general","ad_type":"text","days_active":19,"first_seen":"2026-04-12T05:09:58+00:00","last_seen":"2026-05-01T14:05:03+00:00"},{"id":"9cf09e523d18be49","network":"taboola","advertiser":"cosmetica","advertiser_slug":"cosmetica","title":"Bahara Özel İndirim Zamanı","thumbnail":"/_img/taboola/9cf09e523d18be49","video_url":null,"countries":["TR"],"vertical":"general","ad_type":"text","days_active":23,"first_seen":"2026-04-07T19:34:49+00:00","last_seen":"2026-05-01T13:30:24+00:00"},{"id":"df196c8ed382f1d6","network":"taboola","advertiser":"Tokyo Nights","advertiser_slug":"tokyo-nights","title":"For One Night, London Disappears. You’re in Tokyo","thumbnail":"/_img/taboola/df196c8ed382f1d6","video_url":null,"countries":["GB"],"vertical":"general","ad_type":"text","days_active":8,"first_seen":"2026-04-23T10:18:58+00:00","last_seen":"2026-05-01T13:09:27+00:00"},{"id":"63cda8fa231e149c","network":"taboola","advertiser":"www.tello.com","advertiser_slug":"www-tello-com","title":"Stop Paying for Data You Don't Need. Build Your Custom 5G Plan Starting at $5/mo","thumbnail":"/_img/taboola/63cda8fa231e149c","video_url":null,"countries":["US"],"vertical":"tech","ad_type":"text","days_active":16,"first_seen":"2026-04-15T08:48:20+00:00","last_seen":"2026-05-01T12:55:39+00:00"},{"id":"261aaebe2d4e18b1","network":"taboola","advertiser":"PureTopics | Search Ads","advertiser_slug":"puretopics-search-ads","title":"Search for Small Ship Cruise Lines","thumbnail":"/_img/taboola/261aaebe2d4e18b1","video_url":null,"countries":["US"],"vertical":"travel","ad_type":"text","days_active":18,"first_seen":"2026-04-12T14:13:29+00:00","last_seen":"2026-05-01T12:48:33+00:00"},{"id":"8056c18d2a95d919","network":"taboola","advertiser":"BuzzNFun.com","advertiser_slug":"buzznfun-com","title":"Vintage Photos Of Most Beautiful Female Icons","thumbnail":"/_img/taboola/8056c18d2a95d919","video_url":null,"countries":["AU","BE","BR","CL","CZ","GB","GR","IN","KR","NL","NO","PL","QA","SK","TR","TW","US","ZA"],"vertical":"general","ad_type":"photo","days_active":14,"first_seen":"2026-04-17T11:29:22+00:00","last_seen":"2026-05-01T12:46:54+00:00"},{"id":"761c418126fda4c4","network":"taboola","advertiser":"AmberArt","advertiser_slug":"amberart","title":"Men Didn’t Expect These Shorts to Feel This Comfortable","thumbnail":"/_img/taboola/761c418126fda4c4","video_url":null,"countries":["US"],"vertical":"general","ad_type":"text","days_active":21,"first_seen":"2026-04-09T23:27:55+00:00","last_seen":"2026-05-01T12:41:18+00:00"},{"id":"4b418167466aa16a","network":"taboola","advertiser":"cosmetica","advertiser_slug":"cosmetica","title":"Güzellikte Büyük Nisan İndirimi!","thumbnail":"/_img/taboola/4b418167466aa16a","video_url":null,"countries":["TR"],"vertical":"general","ad_type":"text","days_active":22,"first_seen":"2026-04-08T20:33:10+00:00","last_seen":"2026-05-01T12:12:20+00:00"},{"id":"39de00c1c8c44521","network":"taboola","advertiser":"Gesundheitsjournal","advertiser_slug":"gesundheitsjournal","title":"Warum immer mehr Deutsche auf dieses Schlaf-Pflaster setzen - aufkleben und einschlafen!","thumbnail":"/_img/taboola/39de00c1c8c44521","video_url":null,"countries":["DE"],"vertical":"general","ad_type":"text","days_active":2,"first_seen":"2026-04-29T10:56:42+00:00","last_seen":"2026-05-01T12:09:04+00:00"},{"id":"786d56fb396c98f6","network":"taboola","advertiser":"Funlyfun","advertiser_slug":"funlyfun","title":"Silver Hair, Golden Years: Why Dating Apps Are Shifting to Mature Singles","thumbnail":"/_img/taboola/786d56fb396c98f6","video_url":null,"countries":["US"],"vertical":"general","ad_type":"text","days_active":9,"first_seen":"2026-04-21T17:02:00+00:00","last_seen":"2026-05-01T12:05:39+00:00"},{"id":"56bc9d9e7e6ab015","network":"taboola","advertiser":"Gesundheitsjournal","advertiser_slug":"gesundheitsjournal","title":"Schlaf-Experte sagt: Dieses Pflaster lässt Sie endlich durchschlafen (kein Melatonin)","thumbnail":"/_img/taboola/56bc9d9e7e6ab015","video_url":null,"countries":["DE"],"vertical":"general","ad_type":"text","days_active":3,"first_seen":"2026-04-27T23:45:50+00:00","last_seen":"2026-05-01T11:51:00+00:00"},{"id":"7cddd39423817dc5","network":"taboola","advertiser":"PureTopics | Search Ads","advertiser_slug":"puretopics-search-ads","title":"Search for Birth Injury Lawyer Near Me","thumbnail":"/_img/taboola/7cddd39423817dc5","video_url":null,"countries":["US"],"vertical":"legal","ad_type":"text","days_active":18,"first_seen":"2026-04-12T16:40:41+00:00","last_seen":"2026-05-01T11:49:53+00:00"},{"id":"413d4f2afcbe754d","network":"taboola","advertiser":"Consejos y Trucos","advertiser_slug":"consejos-y-trucos","title":"Piratas intentan abordar un crucero, pero no contaban con que había un veterano a bordo.","thumbnail":"/_img/taboola/413d4f2afcbe754d","video_url":null,"countries":["ES"],"vertical":"general","ad_type":"text","days_active":19,"first_seen":"2026-04-12T09:30:17+00:00","last_seen":"2026-05-01T11:34:07+00:00"},{"id":"6e11d63d36a0d387","network":"taboola","advertiser":"Ratgeber für zuhause","advertiser_slug":"ratgeber-f-r-zuhause","title":"Wie deutsche Hausmeister Toiletten blitzblank halten, ohne sie anzufassen","thumbnail":"/_img/taboola/6e11d63d36a0d387","video_url":null,"countries":["DE"],"vertical":"general","ad_type":"text","days_active":15,"first_seen":"2026-04-16T08:03:15+00:00","last_seen":"2026-05-01T11:32:20+00:00"},{"id":"f3096ad53019e2eb","network":"taboola","advertiser":"Loona's Naturkosmetik","advertiser_slug":"loona-s-naturkosmetik","title":"Haarwachstum: Was unsere Großmütter wussten – und was wir vergessen haben.","thumbnail":"/_img/taboola/f3096ad53019e2eb","video_url":null,"countries":["DE"],"vertical":"general","ad_type":"text","days_active":19,"first_seen":"2026-04-11T19:18:44+00:00","last_seen":"2026-05-01T11:14:29+00:00"},{"id":"651ca89f9372d68f","network":"taboola","advertiser":"US Food Search","advertiser_slug":"us-food-search","title":"Elephant Digs For 11 Hours And Gets This Out","thumbnail":"/_img/taboola/651ca89f9372d68f","video_url":null,"countries":["BE","BG","BR","CZ","DE","ES","FI","FR","GR","HU","IE","MX","NL","NO","NZ","PL","PT","QA","RO","SE","SK","TR","TW","US","ZA"],"vertical":"general","ad_type":"text","days_active":24,"first_seen":"2026-04-07T00:27:06+00:00","last_seen":"2026-05-01T10:55:17+00:00"},{"id":"4dc4c93b3dc3205d","network":"taboola","advertiser":"Hair restoration","advertiser_slug":"hair-restoration","title":"Saç Restorasyonu Nasıl Çalışır","thumbnail":"/_img/taboola/4dc4c93b3dc3205d","video_url":null,"countries":["TR"],"vertical":"general","ad_type":"text","days_active":3,"first_seen":"2026-04-28T06:35:04+00:00","last_seen":"2026-05-01T10:46:18+00:00"},{"id":"98ab24a3b9fc709e","network":"taboola","advertiser":"Orivelle","advertiser_slug":"orivelle","title":"Nail Care Expert: If You Have Nail Fungus, Try This Tonight (At Home)","thumbnail":"/_img/taboola/98ab24a3b9fc709e","video_url":null,"countries":["AU","DE","FR","GB","GR","NO","NZ"],"vertical":"auto","ad_type":"text","days_active":24,"first_seen":"2026-04-07T08:39:14+00:00","last_seen":"2026-05-01T10:43:07+00:00"},{"id":"c206d972ec259264","network":"taboola","advertiser":"Complex Law","advertiser_slug":"complex-law","title":"We Could Find (2) Mis-Sold Car Finance Agreements In Your Name","thumbnail":"/_img/taboola/c206d972ec259264","video_url":null,"countries":["GB"],"vertical":"auto","ad_type":"text","days_active":23,"first_seen":"2026-04-07T16:47:04+00:00","last_seen":"2026-05-01T10:21:56+00:00"},{"id":"0d7724faaf791738","network":"taboola","advertiser":"PureTopics | Search Ads","advertiser_slug":"puretopics-search-ads","title":"Search for Small Ship Cruise Lines","thumbnail":"/_img/taboola/0d7724faaf791738","video_url":null,"countries":["US"],"vertical":"travel","ad_type":"text","days_active":21,"first_seen":"2026-04-10T04:21:32+00:00","last_seen":"2026-05-01T10:15:31+00:00"},{"id":"407c950bea42d3a7","network":"taboola","advertiser":"pcwelt","advertiser_slug":"pcwelt","title":"OMEN HyperX: Zuverlässige Gaming-Leistung im Alltag","thumbnail":"/_img/taboola/407c950bea42d3a7","video_url":null,"countries":["DE"],"vertical":"general","ad_type":"text","days_active":1,"first_seen":"2026-04-29T13:08:01+00:00","last_seen":"2026-05-01T09:55:10+00:00"},{"id":"e996c1345bdbc7d0","network":"taboola","advertiser":"Osteo Research","advertiser_slug":"osteo-research","title":"Top MD: This 1 Mineral Reduces Knee Pain \"Unlike Any other\"","thumbnail":"/_img/taboola/e996c1345bdbc7d0","video_url":null,"countries":["US"],"vertical":"general","ad_type":"text","days_active":3,"first_seen":"2026-04-27T11:09:46+00:00","last_seen":"2026-05-01T09:31:05+00:00"},{"id":"053176dedb2b97b6","network":"taboola","advertiser":"Heatpumps beste Angebote","advertiser_slug":"heatpumps-beste-angebote","title":"Hessen beschließt Wärmepumpen-Paket für Eigenheimbesitzer (im Überblick)","thumbnail":"/_img/taboola/053176dedb2b97b6","video_url":null,"countries":["DE"],"vertical":"general","ad_type":"text","days_active":18,"first_seen":"2026-04-12T17:07:35+00:00","last_seen":"2026-05-01T09:02:05+00:00"},{"id":"4f318be261747aa2","network":"taboola","advertiser":"Heatpumps beste Angebote","advertiser_slug":"heatpumps-beste-angebote","title":"Hessen beschließt Wärmepumpen-Paket für Eigenheimbesitzer (im Überblick)","thumbnail":"/_img/taboola/4f318be261747aa2","video_url":null,"countries":["DE"],"vertical":"general","ad_type":"text","days_active":24,"first_seen":"2026-04-06T22:07:36+00:00","last_seen":"2026-05-01T08:56:44+00:00"},{"id":"dc65011233cbdcc5","network":"taboola","advertiser":"Trending in Australia","advertiser_slug":"trending-in-australia","title":"This New Sciatica Device Is Getting Attention Across Australia","thumbnail":"/_img/taboola/dc65011233cbdcc5","video_url":null,"countries":["AU"],"vertical":"general","ad_type":"text","days_active":21,"first_seen":"2026-04-10T06:11:57+00:00","last_seen":"2026-05-01T08:54:38+00:00"},{"id":"827a0d66d56f3a60","network":"taboola","advertiser":"Complex Law","advertiser_slug":"complex-law","title":"This Tool Searches Your Old Car Finance Deals & Flags Any Potential Refunds","thumbnail":"/_img/taboola/827a0d66d56f3a60","video_url":null,"countries":["GB"],"vertical":"auto","ad_type":"text","days_active":23,"first_seen":"2026-04-07T16:47:07+00:00","last_seen":"2026-05-01T08:46:53+00:00"},{"id":"c4f986139779959a","network":"taboola","advertiser":"Nachbarsmatch","advertiser_slug":"nachbarsmatch","title":"Frankfurt Am Main : Eine Dating-Website für über 40-jährige, die wirklich funktioniert","thumbnail":"/_img/taboola/c4f986139779959a","video_url":null,"countries":["DE"],"vertical":"general","ad_type":"text","days_active":16,"first_seen":"2026-04-14T09:04:48+00:00","last_seen":"2026-05-01T08:39:28+00:00"},{"id":"97cdfbfb8ade1447","network":"taboola","advertiser":"Map in Pocket","advertiser_slug":"map-in-pocket","title":"Türkiye gerçek katarakt ameliyatı maliyeti 2026 nedir","thumbnail":"/_img/taboola/97cdfbfb8ade1447","video_url":null,"countries":["TR"],"vertical":"general","ad_type":"text","days_active":24,"first_seen":"2026-04-07T00:05:49+00:00","last_seen":"2026-05-01T08:38:47+00:00"},{"id":"140daa8e21ba3a0f","network":"taboola","advertiser":"Lingxi Games","advertiser_slug":"lingxi-games","title":"Global Success for Lingxi","thumbnail":"/_img/taboola/140daa8e21ba3a0f","video_url":null,"countries":["BE","BG","CZ","DK","ES","FI","FR","GR","HU","IE","IT","NL","SG","TW"],"vertical":"general","ad_type":"text","days_active":10,"first_seen":"2026-04-20T19:21:25+00:00","last_seen":"2026-05-01T08:25:51+00:00"},{"id":"d6ce33b74d26f403","network":"taboola","advertiser":"Apartamentos | Enlaces Publicitarios","advertiser_slug":"apartamentos-enlaces-publicitarios","title":"Guía esencial de apartamentos en venta en Chile 2026","thumbnail":"/_img/taboola/d6ce33b74d26f403","video_url":null,"countries":["CL"],"vertical":"general","ad_type":"text","days_active":17,"first_seen":"2026-04-13T13:33:11+00:00","last_seen":"2026-05-01T08:19:59+00:00"},{"id":"1ebf734d904adfc1","network":"taboola","advertiser":"Apartamentos | Enlaces Publicitarios","advertiser_slug":"apartamentos-enlaces-publicitarios","title":"Guía esencial de apartamentos en venta en Chile 2026","thumbnail":"/_img/taboola/1ebf734d904adfc1","video_url":null,"countries":["CL"],"vertical":"general","ad_type":"text","days_active":17,"first_seen":"2026-04-13T13:31:55+00:00","last_seen":"2026-05-01T08:16:01+00:00"},{"id":"dbb5026423a0e166","network":"taboola","advertiser":"Araba Değeri  | Arama Reklamları","advertiser_slug":"araba-de-eri-arama-reklamlar","title":"Arabanızın 2026'daki Gerçek Değeri Ne Kadar?","thumbnail":"/_img/taboola/dbb5026423a0e166","video_url":null,"countries":["TR"],"vertical":"general","ad_type":"photo","days_active":13,"first_seen":"2026-04-17T09:47:52+00:00","last_seen":"2026-05-01T08:04:47+00:00"},{"id":"b23aae563307cbff","network":"taboola","advertiser":"interactive brokers","advertiser_slug":"interactive-brokers","title":"Open an Account Now!","thumbnail":"/_img/taboola/b23aae563307cbff","video_url":null,"countries":["SG"],"vertical":"general","ad_type":"text","days_active":17,"first_seen":"2026-04-14T03:30:59+00:00","last_seen":"2026-05-01T07:59:34+00:00"},{"id":"88e1dc9fca0f0ac6","network":"taboola","advertiser":"TopGentlemen.com","advertiser_slug":"topgentlemen-com","title":"These 10 yachts are the most expensive luxury vessels ever","thumbnail":"/_img/taboola/88e1dc9fca0f0ac6","video_url":null,"countries":["BE","GB"],"vertical":"general","ad_type":"photo","days_active":17,"first_seen":"2026-04-13T19:39:15+00:00","last_seen":"2026-05-01T07:52:32+00:00"},{"id":"5c4e654eba19dacb","network":"taboola","advertiser":"foodisinthehouse","advertiser_slug":"foodisinthehouse","title":"בתי אבות בישראל: טווח מחירים והשוואה","thumbnail":"/_img/taboola/5c4e654eba19dacb","video_url":null,"countries":["IL"],"vertical":"general","ad_type":"text","days_active":19,"first_seen":"2026-04-11T18:53:50+00:00","last_seen":"2026-05-01T07:02:15+00:00"},{"id":"c8f3a0a1eeced3e3","network":"taboola","advertiser":"dropyourpounds","advertiser_slug":"dropyourpounds","title":"Too Busy to Diet. Not Too Busy to Stick a Patch On.","thumbnail":"/_img/taboola/c8f3a0a1eeced3e3","video_url":null,"countries":["US"],"vertical":"health","ad_type":"text","days_active":14,"first_seen":"2026-04-17T04:41:05+00:00","last_seen":"2026-05-01T06:55:28+00:00"},{"id":"2c9eae3b5ec827b2","network":"taboola","advertiser":"NNGRSRT - GrannyPods_US","advertiser_slug":"nngrsrt-grannypods-us","title":"Granny Pods in the U.S. – A Growing Solution for Affordable Senior Living at Home","thumbnail":"/_img/taboola/2c9eae3b5ec827b2","video_url":null,"countries":["AU","BE","BG","BR","CL","CZ","FI","FR","GB","GR","HU","IE","IN","JP","KR","MX","NL","NZ","PL","QA","RO","SG","SK","TH","TR","TW","US","ZA"],"vertical":"general","ad_type":"text","days_active":24,"first_seen":"2026-04-07T00:44:08+00:00","last_seen":"2026-05-01T06:45:36+00:00"},{"id":"c9204dbdfbf73d10","network":"taboola","advertiser":"르매리","advertiser_slug":"unknown","title":"이혼한지 1년 이상 된","thumbnail":"/_img/taboola/c9204dbdfbf73d10","video_url":null,"countries":["KR"],"vertical":"general","ad_type":"text","days_active":17,"first_seen":"2026-04-13T17:24:40+00:00","last_seen":"2026-05-01T06:30:08+00:00"},{"id":"d241ac348f96e91b","network":"taboola","advertiser":"Südtirol","advertiser_slug":"s-dtirol","title":"Alpenlente in Zuid-Tirol, Italië","thumbnail":"/_img/taboola/d241ac348f96e91b","video_url":null,"countries":["NL"],"vertical":"general","ad_type":"text","days_active":19,"first_seen":"2026-04-11T23:02:49+00:00","last_seen":"2026-05-01T06:27:56+00:00"},{"id":"e2cdefa2fb711ec3","network":"taboola","advertiser":"Gentside","advertiser_slug":"gentside","title":"Mentale Aussetzer? Neue Zweifel an Donald Trumps Zustand","thumbnail":"/_img/taboola/e2cdefa2fb711ec3","video_url":null,"countries":["DE"],"vertical":"general","ad_type":"text","days_active":16,"first_seen":"2026-04-14T16:19:26+00:00","last_seen":"2026-05-01T06:12:14+00:00"},{"id":"5c0a48fc4abb5031","network":"taboola","advertiser":"Factinate","advertiser_slug":"factinate","title":"England’s Most Tragic Queen, Elizabeth Woodville","thumbnail":"/_img/taboola/5c0a48fc4abb5031","video_url":null,"countries":["US"],"vertical":"general","ad_type":"text","days_active":18,"first_seen":"2026-04-12T08:17:00+00:00","last_seen":"2026-05-01T06:03:11+00:00"},{"id":"e9fd9f392a635e7c","network":"taboola","advertiser":"KOMPASS Karten","advertiser_slug":"kompass-karten","title":"Darum solltest Du Urlaub in Südtirols Süden machen","thumbnail":"/_img/taboola/e9fd9f392a635e7c","video_url":null,"countries":["DE"],"vertical":"general","ad_type":"text","days_active":18,"first_seen":"2026-04-12T23:09:51+00:00","last_seen":"2026-05-01T05:54:53+00:00"},{"id":"2df4021f21f7cc27","network":"taboola","advertiser":"Trending in Australia","advertiser_slug":"trending-in-australia","title":"If You Have Sciatica Pain, Do This Bedtime Trick Tonight","thumbnail":"/_img/taboola/2df4021f21f7cc27","video_url":null,"countries":["AU"],"vertical":"general","ad_type":"text","days_active":16,"first_seen":"2026-04-14T23:17:26+00:00","last_seen":"2026-05-01T05:48:47+00:00"},{"id":"0e02c0f80a7c92be","network":"taboola","advertiser":"Banamex","advertiser_slug":"banamex","title":"Checa esta tarjeta sin anualidad.","thumbnail":"/_img/taboola/0e02c0f80a7c92be","video_url":null,"countries":["MX"],"vertical":"general","ad_type":"text","days_active":23,"first_seen":"2026-04-07T06:51:59+00:00","last_seen":"2026-05-01T05:42:49+00:00"},{"id":"91eb9f27ac8f481d","network":"taboola","advertiser":"Map in Pocket","advertiser_slug":"map-in-pocket","title":"Türkiye’nin en iyi göz hastaneleri: İstanbul’da tedavi için nereye gitmeli?","thumbnail":"/_img/taboola/91eb9f27ac8f481d","video_url":null,"countries":["TR"],"vertical":"general","ad_type":"text","days_active":24,"first_seen":"2026-04-07T03:05:08+00:00","last_seen":"2026-05-01T05:41:57+00:00"},{"id":"05159ff5ba33e15d","network":"taboola","advertiser":"YUKINOUE","advertiser_slug":"yukinoue","title":"No spots  \"Just apply this gel\"— 7 days later, unbelievable","thumbnail":"/_img/taboola/05159ff5ba33e15d","video_url":null,"countries":["SG"],"vertical":"general","ad_type":"text","days_active":17,"first_seen":"2026-04-13T20:40:17+00:00","last_seen":"2026-05-01T05:34:02+00:00"},{"id":"615f2e199dba5e8f","network":"taboola","advertiser":"Gentside","advertiser_slug":"gentside","title":"Donald Trump immer verwirrter: \"Teile seines Gehirn funktionieren nicht mehr!\"","thumbnail":"/_img/taboola/615f2e199dba5e8f","video_url":null,"countries":["DE"],"vertical":"general","ad_type":"text","days_active":19,"first_seen":"2026-04-11T21:10:51+00:00","last_seen":"2026-05-01T05:15:21+00:00"},{"id":"5fab9adfa6a06031","network":"taboola","advertiser":"Timeshare Exit Firm","advertiser_slug":"timeshare-exit-firm","title":"Former Resort Employee Reveals What Owners Are Never Told","thumbnail":"/_img/taboola/5fab9adfa6a06031","video_url":null,"countries":["US"],"vertical":"general","ad_type":"text","days_active":24,"first_seen":"2026-04-07T00:01:22+00:00","last_seen":"2026-05-01T05:10:27+00:00"},{"id":"ad2970a36e0ab2fe","network":"taboola","advertiser":"Intuit Credit Karma","advertiser_slug":"intuit-credit-karma","title":"7 Best Car Insurance Companies","thumbnail":"/_img/taboola/ad2970a36e0ab2fe","video_url":null,"countries":["US"],"vertical":"finance","ad_type":"text","days_active":21,"first_seen":"2026-04-09T10:41:17+00:00","last_seen":"2026-05-01T05:09:38+00:00"},{"id":"cf4ab4cc0147135f","network":"taboola","advertiser":"americ24","advertiser_slug":"americ24","title":"The Early registration of the Green Card Lottery has begun.","thumbnail":"/_img/taboola/cf4ab4cc0147135f","video_url":null,"countries":["BE","DK","FI","NO"],"vertical":"auto","ad_type":"text","days_active":23,"first_seen":"2026-04-08T04:07:58+00:00","last_seen":"2026-05-01T05:02:27+00:00"},{"id":"89ab85c6b8bb1ba7","network":"taboola","advertiser":"Calenruy","advertiser_slug":"calenruy","title":"Mercado Libre CFD: Calcula cuánto podrías ganar invirtiendo solo $100","thumbnail":"/_img/taboola/89ab85c6b8bb1ba7","video_url":null,"countries":["CL"],"vertical":"general","ad_type":"text","days_active":10,"first_seen":"2026-04-20T07:13:15+00:00","last_seen":"2026-05-01T04:58:58+00:00"},{"id":"bbd24a7097174820","network":"taboola","advertiser":"HOME4U不動産売却","advertiser_slug":"home4u","title":"売る前に必ず確認！不動産売却のNG行動とは？","thumbnail":"/_img/taboola/bbd24a7097174820","video_url":null,"countries":["JP"],"vertical":"general","ad_type":"text","days_active":19,"first_seen":"2026-04-12T01:34:55+00:00","last_seen":"2026-05-01T04:58:04+00:00"},{"id":"50a7bea1aedc7bb5","network":"taboola","advertiser":"Araba Değeri  | Arama Reklamları","advertiser_slug":"araba-de-eri-arama-reklamlar","title":"Arabanızın Değerini Kontrol Edin","thumbnail":"/_img/taboola/50a7bea1aedc7bb5","video_url":null,"countries":["TR"],"vertical":"general","ad_type":"photo","days_active":13,"first_seen":"2026-04-17T09:44:55+00:00","last_seen":"2026-05-01T04:50:39+00:00"},{"id":"535fe7fbb382b4db","network":"taboola","advertiser":"Esslyn HydroJet Max","advertiser_slug":"esslyn-hydrojet-max","title":"Die geniale Erfindung, die jeden Gartenschlauch in einen Hochdruckreiniger verwandelt","thumbnail":"/_img/taboola/535fe7fbb382b4db","video_url":null,"countries":["DE"],"vertical":"general","ad_type":"text","days_active":8,"first_seen":"2026-04-22T19:41:21+00:00","last_seen":"2026-05-01T04:47:53+00:00"},{"id":"46dddd6bfd72b6d9","network":"taboola","advertiser":"Esslyn HydroJet Max","advertiser_slug":"esslyn-hydrojet-max","title":"Das Must-have für Ihre gründliche Außenreinigung 2026","thumbnail":"/_img/taboola/46dddd6bfd72b6d9","video_url":null,"countries":["DE"],"vertical":"general","ad_type":"text","days_active":2,"first_seen":"2026-04-28T10:09:18+00:00","last_seen":"2026-05-01T04:10:37+00:00"},{"id":"8a448b429d7cafb5","network":"taboola","advertiser":"Financial News Now","advertiser_slug":"financial-news-now","title":"Investing In AI Infrastructure Is Driving Unprecedented Profit Potential For Investors","thumbnail":"/_img/taboola/8a448b429d7cafb5","video_url":null,"countries":["US"],"vertical":"general","ad_type":"text","days_active":23,"first_seen":"2026-04-07T04:10:23+00:00","last_seen":"2026-05-01T03:58:22+00:00"},{"id":"905cc8b1169fbdd0","network":"taboola","advertiser":"Review Beauty","advertiser_slug":"review-beauty","title":"Why thousands of women are switching to this bra","thumbnail":"/_img/taboola/905cc8b1169fbdd0","video_url":null,"countries":["AT","AU","BE","BG","BR","CA","CH","CL","CZ","DK","ES","FI","GB","GR","HU","IE","IL","IN","IT","JP","KR","MX","NL","NO","NZ","PL","PT","QA","RO","SE","SG","SK","TH","TR","TW","ZA"],"vertical":"general","ad_type":"text","days_active":24,"first_seen":"2026-04-07T00:13:19+00:00","last_seen":"2026-05-01T03:58:05+00:00"},{"id":"deca32754cde6393","network":"taboola","advertiser":"Review Beauty","advertiser_slug":"review-beauty","title":"This anti-sagging bra is so comfy, women won't take it off — even at night !","thumbnail":"/_img/taboola/deca32754cde6393","video_url":null,"countries":["AT","AU","BE","BG","BR","CH","CL","CZ","DK","ES","FI","GB","GR","HU","IE","IL","IN","IT","JP","KR","MX","NL","NO","PL","PT","QA","RO","SE","SG","SK","TH","TR","TW","ZA"],"vertical":"general","ad_type":"text","days_active":23,"first_seen":"2026-04-07T07:17:09+00:00","last_seen":"2026-05-01T03:58:05+00:00"},{"id":"3b70896712f0d870","network":"taboola","advertiser":"Review Beauty","advertiser_slug":"review-beauty","title":"The bra everyone's talking about — and it's selling out fast !","thumbnail":"/_img/taboola/3b70896712f0d870","video_url":null,"countries":["BE","BG","BR","CH","CL","CZ","DK","FI","GR","HU","IE","IN","JP","KR","MX","NL","NO","PL","PT","QA","RO","SE","SG","SK","TH","TR","TW","ZA"],"vertical":"general","ad_type":"text","days_active":24,"first_seen":"2026-04-07T03:38:11+00:00","last_seen":"2026-05-01T03:56:12+00:00"},{"id":"05449246b8d882ed","network":"taboola","advertiser":"Review Beauty","advertiser_slug":"review-beauty","title":"Why thousands of women are switching to this bra","thumbnail":"/_img/taboola/05449246b8d882ed","video_url":null,"countries":["AT","AU","BE","BG","BR","CA","CH","CL","CZ","DK","ES","FI","FR","GB","GR","HU","IE","IL","IN","IT","JP","KR","MX","NL","NO","PL","PT","QA","RO","SE","SG","SK","TH","TR","TW","US","ZA"],"vertical":"general","ad_type":"text","days_active":24,"first_seen":"2026-04-07T00:01:24+00:00","last_seen":"2026-05-01T03:54:08+00:00"},{"id":"52e581e2ead40767","network":"taboola","advertiser":"Review Beauty","advertiser_slug":"review-beauty","title":"The bra everyone's talking about — and it's selling out fast !","thumbnail":"/_img/taboola/52e581e2ead40767","video_url":null,"countries":["AT","BE","BG","BR","CA","CH","CL","CZ","DK","ES","FI","FR","GB","GR","HU","IE","IL","IN","IT","JP","KR","MX","NL","NO","PL","PT","QA","RO","SE","SG","SK","TH","TR","TW","ZA"],"vertical":"general","ad_type":"text","days_active":24,"first_seen":"2026-04-07T03:34:04+00:00","last_seen":"2026-05-01T03:50:02+00:00"},{"id":"e13d836b9733d1b5","network":"taboola","advertiser":"Review Beauty","advertiser_slug":"review-beauty","title":"This anti-sagging bra is so comfy, women won't take it off — even at night !","thumbnail":"/_img/taboola/e13d836b9733d1b5","video_url":null,"countries":["AU","BE","BG","BR","CA","CH","CL","CZ","DK","ES","FI","GB","GR","HU","IE","IL","IN","IT","JP","KR","MX","NL","NO","PL","PT","QA","RO","SE","SG","SK","TH","TR","TW","US","ZA"],"vertical":"general","ad_type":"text","days_active":24,"first_seen":"2026-04-07T03:06:25+00:00","last_seen":"2026-05-01T03:46:42+00:00"},{"id":"f626d18c275eeb72","network":"taboola","advertiser":"Review Beauty","advertiser_slug":"review-beauty","title":"The bra everyone's talking about — and it's selling out fast !","thumbnail":"/_img/taboola/f626d18c275eeb72","video_url":null,"countries":["BE","BG","BR","CZ","DK","FI","HU","IE","IN","JP","KR","NL","NO","QA","RO","SG","SK","TH","TR","TW","ZA"],"vertical":"general","ad_type":"text","days_active":21,"first_seen":"2026-04-10T03:24:38+00:00","last_seen":"2026-05-01T03:33:26+00:00"},{"id":"65caf8f65b4473e3","network":"taboola","advertiser":"trendmaze.page","advertiser_slug":"trendmaze-page","title":"Signos que imponen respeto naturalmente","thumbnail":"/_img/taboola/65caf8f65b4473e3","video_url":null,"countries":["ES"],"vertical":"general","ad_type":"photo","days_active":17,"first_seen":"2026-04-13T16:01:44+00:00","last_seen":"2026-05-01T03:27:17+00:00"},{"id":"d23716944b0c3bc2","network":"taboola","advertiser":"BuzznFun.com","advertiser_slug":"buzznfun-com","title":"15 most beautiful women in the world","thumbnail":"/_img/taboola/d23716944b0c3bc2","video_url":null,"countries":["AT","AU","BE","BG","CA","CH","CZ","DK","ES","FI","FR","GB","GR","HU","IE","IL","IT","JP","NL","NO","PL","RO","SG","SK","TH","US"],"vertical":"general","ad_type":"photo","days_active":13,"first_seen":"2026-04-17T11:15:34+00:00","last_seen":"2026-05-01T03:22:16+00:00"},{"id":"ea079ff0f781b036","network":"taboola","advertiser":"Geo","advertiser_slug":"geo","title":"De nouveaux documents démontrent la relation entre Donald Trump et Jeffrey Epstein","thumbnail":"/_img/taboola/ea079ff0f781b036","video_url":null,"countries":["FR"],"vertical":"general","ad_type":"text","days_active":10,"first_seen":"2026-04-20T07:17:43+00:00","last_seen":"2026-05-01T03:20:55+00:00"},{"id":"e704c8c217052047","network":"taboola","advertiser":"swipematch.de","advertiser_slug":"swipematch-de","title":"Warum immer mehr Singles 50+ wieder daten","thumbnail":"/_img/taboola/e704c8c217052047","video_url":null,"countries":["DE"],"vertical":"general","ad_type":"text","days_active":18,"first_seen":"2026-04-12T07:03:08+00:00","last_seen":"2026-05-01T03:11:04+00:00"},{"id":"a7176124f88ea924","network":"taboola","advertiser":"Review Beauty","advertiser_slug":"review-beauty","title":"This posture bra is blowing up — women everywhere are obsessed","thumbnail":"/_img/taboola/a7176124f88ea924","video_url":null,"countries":["AU","BE","BG","BR","CH","CL","CZ","DK","ES","FI","GB","GR","HU","IE","IL","IN","IT","JP","KR","MX","NL","NO","PL","PT","QA","RO","SE","SG","SK","TH","TR","TW","ZA"],"vertical":"general","ad_type":"text","days_active":23,"first_seen":"2026-04-07T06:03:25+00:00","last_seen":"2026-05-01T03:10:09+00:00"},{"id":"865f708b9dff6c27","network":"taboola","advertiser":"Outlier Model","advertiser_slug":"outlier-model","title":"Elefant gräbt 11 Stunden lang ein riesiges Loch und sieht, was dabei herauskommt.","thumbnail":"/_img/taboola/865f708b9dff6c27","video_url":null,"countries":["DE"],"vertical":"general","ad_type":"text","days_active":18,"first_seen":"2026-04-12T06:21:00+00:00","last_seen":"2026-05-01T02:39:05+00:00"},{"id":"d90e73b4351e163d","network":"taboola","advertiser":"Real","advertiser_slug":"real","title":"Keep your mortgage paid - even when sick or injured","thumbnail":"/_img/taboola/d90e73b4351e163d","video_url":null,"countries":["AU"],"vertical":"finance","ad_type":"text","days_active":23,"first_seen":"2026-04-07T09:16:30+00:00","last_seen":"2026-05-01T02:32:07+00:00"},{"id":"c1a67e587345c093","network":"taboola","advertiser":"Real","advertiser_slug":"real","title":"Get up to $15,000 per month if you're sick and can't work","thumbnail":"/_img/taboola/c1a67e587345c093","video_url":null,"countries":["AU"],"vertical":"general","ad_type":"text","days_active":24,"first_seen":"2026-04-07T01:04:07+00:00","last_seen":"2026-05-01T02:28:48+00:00"},{"id":"19777ef88fc129b9","network":"taboola","advertiser":"Locksley Law","advertiser_slug":"locksley-law","title":"We Could Locate (2) Mis-Sold Agreements** Linked To Your Name","thumbnail":"/_img/taboola/19777ef88fc129b9","video_url":null,"countries":["GB"],"vertical":"general","ad_type":"text","days_active":7,"first_seen":"2026-04-23T14:28:51+00:00","last_seen":"2026-05-01T02:27:07+00:00"},{"id":"7890c38cd84db23c","network":"taboola","advertiser":"eToro Market Updates","advertiser_slug":"etoro-market-updates","title":"More Singaporeans Are Trying This Broker. Here’s Why","thumbnail":"/_img/taboola/7890c38cd84db23c","video_url":null,"countries":["SG"],"vertical":"general","ad_type":"text","days_active":17,"first_seen":"2026-04-13T16:39:00+00:00","last_seen":"2026-05-01T02:18:20+00:00"},{"id":"9dd788a927990071","network":"taboola","advertiser":"Friday Plans","advertiser_slug":"friday-plans","title":"Men Born 1949-1984 Can Claim This \"$1 Generic Viagra” At CVS If They Ask","thumbnail":"/_img/taboola/9dd788a927990071","video_url":null,"countries":["US"],"vertical":"legal","ad_type":"text","days_active":7,"first_seen":"2026-04-23T10:25:58+00:00","last_seen":"2026-05-01T02:16:37+00:00"},{"id":"70a183186dc1a978","network":"taboola","advertiser":"eToro Market Updates","advertiser_slug":"etoro-market-updates","title":"eToro Just Landed in Singapore and It’s Regulated","thumbnail":"/_img/taboola/70a183186dc1a978","video_url":null,"countries":["SG"],"vertical":"general","ad_type":"text","days_active":16,"first_seen":"2026-04-14T12:10:37+00:00","last_seen":"2026-05-01T02:14:33+00:00"},{"id":"c2e16742369b4a28","network":"taboola","advertiser":"Nanyang Technological University","advertiser_slug":"nanyang-technological-university","title":"Unlock fintech insights with every topic","thumbnail":"/_img/taboola/c2e16742369b4a28","video_url":null,"countries":["SG"],"vertical":"general","ad_type":"text","days_active":8,"first_seen":"2026-04-23T01:30:16+00:00","last_seen":"2026-05-01T02:14:33+00:00"},{"id":"662fd6d0dcabdf47","network":"taboola","advertiser":"Review Beauty","advertiser_slug":"review-beauty","title":"Why thousands of women are switching to this bra","thumbnail":"/_img/taboola/662fd6d0dcabdf47","video_url":null,"countries":["AU","BE","BG","BR","CL","CZ","DE","DK","FI","FR","GB","GR","HU","IE","IL","IN","IT","JP","KR","MX","NL","NO","PL","PT","QA","RO","SE","SG","SK","TH","TR","TW","ZA"],"vertical":"general","ad_type":"text","days_active":24,"first_seen":"2026-04-07T01:39:00+00:00","last_seen":"2026-05-01T02:14:29+00:00"},{"id":"03e6b775cb85dc2d","network":"taboola","advertiser":"PRIMICIAS","advertiser_slug":"primicias","title":"No te pierdas nada: entra al canal ahora","thumbnail":"/_img/taboola/03e6b775cb85dc2d","video_url":null,"countries":["CL"],"vertical":"general","ad_type":"text","days_active":16,"first_seen":"2026-04-14T09:27:17+00:00","last_seen":"2026-05-01T02:12:40+00:00"},{"id":"89df5dff168f66c1","network":"taboola","advertiser":"LEROY MERLIN","advertiser_slug":"leroy-merlin","title":"Todo sobre los toldos","thumbnail":"/_img/taboola/89df5dff168f66c1","video_url":null,"countries":["ES"],"vertical":"general","ad_type":"text","days_active":18,"first_seen":"2026-04-12T18:57:12+00:00","last_seen":"2026-05-01T01:55:57+00:00"},{"id":"ccf60a8be3762f81","network":"taboola","advertiser":"Titan FX","advertiser_slug":"titan-fx","title":"This Golden Week, your trades are worth more!","thumbnail":"/_img/taboola/ccf60a8be3762f81","video_url":null,"countries":["SG","TW"],"vertical":"general","ad_type":"text","days_active":9,"first_seen":"2026-04-21T09:17:53+00:00","last_seen":"2026-05-01T01:54:41+00:00"},{"id":"d7e0c214f2bf8bf7","network":"taboola","advertiser":"Explored Planet","advertiser_slug":"explored-planet","title":"Rare Unseen Photos Of Historic Figures That Just Surfaced","thumbnail":"/_img/taboola/d7e0c214f2bf8bf7","video_url":null,"countries":["AU","BE","BG","BR","CA","CH","CL","CZ","DE","DK","ES","FI","FR","GB","GR","HU","IE","IN","IT","KR","NL","NO","PL","QA","RO","TH","TR","TW","US","ZA"],"vertical":"general","ad_type":"text","days_active":19,"first_seen":"2026-04-11T13:42:01+00:00","last_seen":"2026-05-01T01:42:17+00:00"},{"id":"afc98f7e953cdff8","network":"taboola","advertiser":"Sharp Mind Report","advertiser_slug":"sharp-mind-report","title":"Neurologists reveal a list of foods that trigger Cognitive Decline. (See which ones).","thumbnail":"/_img/taboola/afc98f7e953cdff8","video_url":null,"countries":["US"],"vertical":"general","ad_type":"text","days_active":12,"first_seen":"2026-04-18T12:52:42+00:00","last_seen":"2026-05-01T01:37:10+00:00"},{"id":"fe21a57c111ada41","network":"taboola","advertiser":"Neural Insight Press","advertiser_slug":"neural-insight-press","title":"The Surprising Root Factor Behind Cognitive Decline and Memory Loss","thumbnail":"/_img/taboola/fe21a57c111ada41","video_url":null,"countries":["US"],"vertical":"general","ad_type":"text","days_active":10,"first_seen":"2026-04-20T17:29:02+00:00","last_seen":"2026-05-01T01:35:23+00:00"},{"id":"964c9fe6e196d87f","network":"taboola","advertiser":"Memory Science Today","advertiser_slug":"memory-science-today","title":"The surprising truth behind forgetfulness and cognitive decline.","thumbnail":"/_img/taboola/964c9fe6e196d87f","video_url":null,"countries":["US"],"vertical":"general","ad_type":"text","days_active":10,"first_seen":"2026-04-20T17:28:25+00:00","last_seen":"2026-05-01T01:35:14+00:00"},{"id":"9670fe3f250d9b8f","network":"taboola","advertiser":"Financial News Now","advertiser_slug":"financial-news-now","title":"The Undervalued Power Provider That AI Hyperscalers May Soon Fight For","thumbnail":"/_img/taboola/9670fe3f250d9b8f","video_url":null,"countries":["US"],"vertical":"general","ad_type":"text","days_active":18,"first_seen":"2026-04-12T08:39:28+00:00","last_seen":"2026-05-01T01:33:13+00:00"},{"id":"a962bdd048108338","network":"taboola","advertiser":"Titan FX","advertiser_slug":"titan-fx","title":"Golden Week Cashback 2026 is now live!","thumbnail":"/_img/taboola/a962bdd048108338","video_url":null,"countries":["SG","TW"],"vertical":"general","ad_type":"text","days_active":9,"first_seen":"2026-04-21T09:18:53+00:00","last_seen":"2026-05-01T01:16:35+00:00"},{"id":"5ab8a8bf64e94e5c","network":"taboola","advertiser":"Yahoo Search","advertiser_slug":"yahoo-search","title":"Recherchez des experts en services gérés IT","thumbnail":"/_img/taboola/5ab8a8bf64e94e5c","video_url":null,"countries":["FR"],"vertical":"general","ad_type":"text","days_active":16,"first_seen":"2026-04-14T22:44:40+00:00","last_seen":"2026-05-01T01:15:25+00:00"},{"id":"b4494535fd242dbe","network":"taboola","advertiser":"BuzznFun.com","advertiser_slug":"buzznfun-com","title":"Top 15 Most Beautiful Women in the World","thumbnail":"/_img/taboola/b4494535fd242dbe","video_url":null,"countries":["AU","BE","BG","CZ","DK","ES","FI","FR","GB","GR","HU","IE","IL","IT","JP","NL","NO","PL","RO","SK","TH"],"vertical":"general","ad_type":"photo","days_active":13,"first_seen":"2026-04-17T11:19:15+00:00","last_seen":"2026-05-01T01:11:47+00:00"},{"id":"71364ba25cb623bf","network":"taboola","advertiser":"People en Español","advertiser_slug":"people-en-espa-ol","title":"5 formas de elevar tu estilo esta primavera","thumbnail":"/_img/taboola/71364ba25cb623bf","video_url":null,"countries":["US"],"vertical":"general","ad_type":"text","days_active":24,"first_seen":"2026-04-07T00:23:05+00:00","last_seen":"2026-05-01T00:57:37+00:00"},{"id":"a45ac83c02ca3cab","network":"taboola","advertiser":"The Memory Index","advertiser_slug":"the-memory-index","title":"Neurologists Beg Senior: Take 1 Tbsp Tonight To Fight Cognitive Decline","thumbnail":"/_img/taboola/a45ac83c02ca3cab","video_url":null,"countries":["US"],"vertical":"general","ad_type":"text","days_active":9,"first_seen":"2026-04-21T12:21:27+00:00","last_seen":"2026-05-01T00:55:34+00:00"},{"id":"6d676ac59e039b97","network":"taboola","advertiser":"Sharp Mind Report","advertiser_slug":"sharp-mind-report","title":"Neurologists release list of common foods that trigger Cognitive Decline. (See which).","thumbnail":"/_img/taboola/6d676ac59e039b97","video_url":null,"countries":["US"],"vertical":"general","ad_type":"text","days_active":13,"first_seen":"2026-04-17T02:46:15+00:00","last_seen":"2026-05-01T00:55:29+00:00"},{"id":"58f6fababa08b786","network":"taboola","advertiser":"Leafguard","advertiser_slug":"leafguard","title":"If You Were Born Before 1970, You May Be Overpaying for Gutter Maintenance","thumbnail":"/_img/taboola/58f6fababa08b786","video_url":null,"countries":["US"],"vertical":"general","ad_type":"text","days_active":7,"first_seen":"2026-04-23T01:34:14+00:00","last_seen":"2026-05-01T00:01:03+00:00"},{"id":"b38b81b8a4874310","network":"taboola","advertiser":"Neuro-Bulletin Online","advertiser_slug":"neuro-bulletin-online","title":"Doctors Identify 10 Medications Now Related to Cognitive Decline (See the List)","thumbnail":"/_img/taboola/b38b81b8a4874310","video_url":null,"countries":["US"],"vertical":"health","ad_type":"text","days_active":9,"first_seen":"2026-04-21T12:25:48+00:00","last_seen":"2026-04-30T23:49:19+00:00"},{"id":"83fdeb5822edc87d","network":"taboola","advertiser":"Senior Savers","advertiser_slug":"senior-savers","title":"If SS income is under $4142 monthly: get 10 listed discounts","thumbnail":"/_img/taboola/83fdeb5822edc87d","video_url":null,"countries":["US"],"vertical":"ecom","ad_type":"text","days_active":20,"first_seen":"2026-04-10T15:51:08+00:00","last_seen":"2026-04-30T23:48:00+00:00"},{"id":"6853c2f19e8de6b4","network":"taboola","advertiser":"Comparisons.org","advertiser_slug":"comparisons-org","title":"Seniors Born Between 1941-1969 Can Receive These 10+ Benefits","thumbnail":"/_img/taboola/6853c2f19e8de6b4","video_url":null,"countries":["US"],"vertical":"general","ad_type":"text","days_active":3,"first_seen":"2026-04-27T11:51:33+00:00","last_seen":"2026-04-30T23:47:35+00:00"},{"id":"c76101e97fa785be","network":"taboola","advertiser":"Gentside","advertiser_slug":"gentside","title":"Nordkorea: Erschreckende Satellitenbilder sorgen für Entsetzen","thumbnail":"/_img/taboola/c76101e97fa785be","video_url":null,"countries":["AT","CH","DE"],"vertical":"general","ad_type":"text","days_active":24,"first_seen":"2026-04-06T22:24:26+00:00","last_seen":"2026-04-30T23:24:30+00:00"},{"id":"b01f6e32289a3c0a","network":"taboola","advertiser":"Review Beauty","advertiser_slug":"review-beauty","title":"This posture bra is blowing up — women everywhere are obsessed","thumbnail":"/_img/taboola/b01f6e32289a3c0a","video_url":null,"countries":["BE","BG","BR","CL","CZ","DK","FI","GR","HU","IE","IN","JP","KR","MX","NL","NO","PL","PT","QA","RO","SG","SK","TH","TR","TW","ZA"],"vertical":"general","ad_type":"text","days_active":22,"first_seen":"2026-04-08T01:57:23+00:00","last_seen":"2026-04-30T23:23:19+00:00"},{"id":"15c21eea67637946","network":"taboola","advertiser":"Financial News Now","advertiser_slug":"financial-news-now","title":"Why The Smart Money Is Tracking This AI Power Play","thumbnail":"/_img/taboola/15c21eea67637946","video_url":null,"countries":["US"],"vertical":"general","ad_type":"text","days_active":18,"first_seen":"2026-04-12T08:15:50+00:00","last_seen":"2026-04-30T23:20:03+00:00"},{"id":"8b743a26edcfe270","network":"taboola","advertiser":"Senior Savers","advertiser_slug":"senior-savers","title":"If SS income is under $4142 monthly: ask for 10 listed discounts","thumbnail":"/_img/taboola/8b743a26edcfe270","video_url":null,"countries":["US"],"vertical":"ecom","ad_type":"text","days_active":23,"first_seen":"2026-04-07T16:26:51+00:00","last_seen":"2026-04-30T23:01:45+00:00"},{"id":"9c7fd86e377ce168","network":"taboola","advertiser":"AmberArt","advertiser_slug":"amberart","title":"Men Didn’t Expect These Shorts to Feel This Comfortable","thumbnail":"/_img/taboola/9c7fd86e377ce168","video_url":null,"countries":["US"],"vertical":"general","ad_type":"text","days_active":21,"first_seen":"2026-04-09T22:57:16+00:00","last_seen":"2026-04-30T23:01:34+00:00"},{"id":"e512b62ad16de7a5","network":"taboola","advertiser":"TopGentlemen.com","advertiser_slug":"topgentlemen-com","title":"The 18 celebrities who found a new path through Islam","thumbnail":"/_img/taboola/e512b62ad16de7a5","video_url":null,"countries":["AU","BE","CZ","DK","FI","FR","GB","GR","HU","IE","IT","JP","NL","NO","PL","SE","SG","SK"],"vertical":"general","ad_type":"photo","days_active":23,"first_seen":"2026-04-07T21:15:43+00:00","last_seen":"2026-04-30T22:58:50+00:00"},{"id":"11238d912df89b13","network":"taboola","advertiser":"Futbol Club Barcelona","advertiser_slug":"futbol-club-barcelona","title":"Spotify Camp Nou experience","thumbnail":"/_img/taboola/11238d912df89b13","video_url":null,"countries":["BE","BG","ES","FR","GB","GR","NL","PL","RO"],"vertical":"general","ad_type":"text","days_active":23,"first_seen":"2026-04-07T18:32:00+00:00","last_seen":"2026-04-30T21:59:57+00:00"},{"id":"63c3846997a66181","network":"taboola","advertiser":"Diavola Pro v3.0","advertiser_slug":"diavola-pro-v3-0","title":"Welcome to the Future of Pizza [Discover]","thumbnail":"/_img/taboola/63c3846997a66181","video_url":null,"countries":["ES","FR","GR","IT","PL"],"vertical":"general","ad_type":"text","days_active":8,"first_seen":"2026-04-22T11:28:25+00:00","last_seen":"2026-04-30T21:58:44+00:00"},{"id":"fb7f76024dc94d28","network":"taboola","advertiser":"Nissan","advertiser_slug":"nissan","title":"Nissan QASHQAI: ricevi l’offerta pensata per te.","thumbnail":"/_img/taboola/fb7f76024dc94d28","video_url":null,"countries":["IT"],"vertical":"general","ad_type":"text","days_active":21,"first_seen":"2026-04-08T23:20:43+00:00","last_seen":"2026-04-30T21:58:08+00:00"},{"id":"2410e32890af5851","network":"taboola","advertiser":"Diavola Pro v3.0","advertiser_slug":"diavola-pro-v3-0","title":"I Finally Get Consistent Pizzeria Crusts [See why]","thumbnail":"/_img/taboola/2410e32890af5851","video_url":null,"countries":["DE","ES","FR","GR","IT","PL"],"vertical":"general","ad_type":"text","days_active":8,"first_seen":"2026-04-22T11:20:47+00:00","last_seen":"2026-04-30T21:48:23+00:00"},{"id":"ae03bbf38fd68fe3","network":"taboola","advertiser":"Blütenwasserbecher","advertiser_slug":"bl-tenwasserbecher","title":"Durstige Bienen: Der einfache Trick, um Ihr Garten-Summen zu retten","thumbnail":"/_img/taboola/ae03bbf38fd68fe3","video_url":null,"countries":["DE"],"vertical":"general","ad_type":"text","days_active":6,"first_seen":"2026-04-24T14:00:07+00:00","last_seen":"2026-04-30T21:48:17+00:00"},{"id":"500cee6efd2f1884","network":"taboola","advertiser":"Futbol Club Barcelona","advertiser_slug":"futbol-club-barcelona","title":"FCB Museum Experience","thumbnail":"/_img/taboola/500cee6efd2f1884","video_url":null,"countries":["BE","ES","GB","GR","NL","PL"],"vertical":"general","ad_type":"text","days_active":23,"first_seen":"2026-04-07T17:43:30+00:00","last_seen":"2026-04-30T21:48:05+00:00"},{"id":"a3152ab7d7a2a984","network":"taboola","advertiser":"Iberostar Beachfront Resorts","advertiser_slug":"iberostar-beachfront-resorts","title":"Take advantage of the deal in Mexico","thumbnail":"/_img/taboola/a3152ab7d7a2a984","video_url":null,"countries":["US"],"vertical":"ecom","ad_type":"text","days_active":23,"first_seen":"2026-04-07T00:06:32+00:00","last_seen":"2026-04-30T21:46:06+00:00"},{"id":"6796cce872da4f14","network":"taboola","advertiser":"Marc O'Polo","advertiser_slug":"marc-o-polo","title":"Marc O'Polo × DFB","thumbnail":"/_img/taboola/6796cce872da4f14","video_url":null,"countries":["ES","IT","NL","PL"],"vertical":"general","ad_type":"text","days_active":20,"first_seen":"2026-04-10T14:58:55+00:00","last_seen":"2026-04-30T21:44:14+00:00"},{"id":"0227cdd7f75a130e","network":"taboola","advertiser":"BuzzNFun.com","advertiser_slug":"buzznfun-com","title":"Stunning Vintage Photos Of Most Beautiful Female Icons","thumbnail":"/_img/taboola/0227cdd7f75a130e","video_url":null,"countries":["AU","BE","BG","BR","CL","GB","GR","HU","IN","KR","MX","NO","PL","QA","RO","TR","TW","ZA"],"vertical":"general","ad_type":"photo","days_active":13,"first_seen":"2026-04-17T10:58:27+00:00","last_seen":"2026-04-30T21:37:37+00:00"},{"id":"e4373be8ae63c037","network":"taboola","advertiser":"Marc O'Polo","advertiser_slug":"marc-o-polo","title":"Natürlich präsent","thumbnail":"/_img/taboola/e4373be8ae63c037","video_url":null,"countries":["AT","CH","DE"],"vertical":"general","ad_type":"text","days_active":20,"first_seen":"2026-04-10T15:21:51+00:00","last_seen":"2026-04-30T21:36:51+00:00"},{"id":"44038bb7742add69","network":"taboola","advertiser":"Very Mobile","advertiser_slug":"very-mobile","title":"Passa a Very: per te 200 Giga, minuti e SMS illimitati a 4,99€ al mese per sempre","thumbnail":"/_img/taboola/44038bb7742add69","video_url":null,"countries":["IT"],"vertical":"general","ad_type":"text","days_active":13,"first_seen":"2026-04-17T16:30:14+00:00","last_seen":"2026-04-30T21:27:24+00:00"},{"id":"ffaf4b460fa9fb30","network":"taboola","advertiser":"Marc O'Polo","advertiser_slug":"marc-o-polo","title":"Natuurlijk aanwezig","thumbnail":"/_img/taboola/ffaf4b460fa9fb30","video_url":null,"countries":["NL"],"vertical":"general","ad_type":"text","days_active":19,"first_seen":"2026-04-11T19:45:12+00:00","last_seen":"2026-04-30T21:22:06+00:00"},{"id":"e3ec08d580ac168c","network":"taboola","advertiser":"Real","advertiser_slug":"real","title":"Cover up to $15,000 per month if you get sick and can't work","thumbnail":"/_img/taboola/e3ec08d580ac168c","video_url":null,"countries":["AU"],"vertical":"general","ad_type":"text","days_active":21,"first_seen":"2026-04-09T16:17:21+00:00","last_seen":"2026-04-30T21:21:58+00:00"},{"id":"1709ca74a474b238","network":"taboola","advertiser":"GMF Assurance Habitation","advertiser_slug":"gmf-assurance-habitation","title":"GMF : assurez votre logement dès 12,24€/mois et profitez de 2 mois offerts","thumbnail":"/_img/taboola/1709ca74a474b238","video_url":null,"countries":["FR"],"vertical":"general","ad_type":"text","days_active":23,"first_seen":"2026-04-07T00:35:10+00:00","last_seen":"2026-04-30T21:18:11+00:00"},{"id":"41d64c6a5068993f","network":"taboola","advertiser":"Rak'n'Roll","advertiser_slug":"rak-n-roll","title":"Daj 1.5% z siebie","thumbnail":"/_img/taboola/41d64c6a5068993f","video_url":null,"countries":["PL"],"vertical":"general","ad_type":"text","days_active":18,"first_seen":"2026-04-11T22:01:11+00:00","last_seen":"2026-04-30T21:17:26+00:00"}]}