{"slug":"carroll-o-dea-lawyers","name":"Carroll & O'Dea Lawyers","ad_count":4,"networks":["taboola"],"countries":["AU"],"verticals":["auto","finance"],"ads":[{"id":"0c8120796cd2831b","network":"taboola","thumbnail":"/_img/taboola/0c8120796cd2831b","video_url":null,"title":"How Tasmanians can claim for workers compensation","countries":["AU"],"last_seen":"2026-05-07T10:45:04+00:00"},{"id":"3fb27809dcb18ca4","network":"taboola","thumbnail":"/_img/taboola/3fb27809dcb18ca4","video_url":null,"title":"Top Tips and Tricks for Making a Successful Travel Insurance Claim","countries":["AU"],"last_seen":"2026-05-07T10:43:36+00:00"},{"id":"c7ad647011d7de5f","network":"taboola","thumbnail":"/_img/taboola/c7ad647011d7de5f","video_url":null,"title":"Is your credit card travel insurance enough?","countries":["AU"],"last_seen":"2026-05-07T10:41:59+00:00"},{"id":"80db91f6cda9208d","network":"taboola","thumbnail":"/_img/taboola/80db91f6cda9208d","video_url":null,"title":"Response to final NSW Birth Trauma Inquiry report","countries":["AU"],"last_seen":"2026-05-07T10:22:16+00:00"}]}