{"slug":"cordelia-cruises","name":"Cordelia Cruises","ad_count":4,"networks":["taboola"],"countries":["IN"],"verticals":["travel"],"ads":[{"id":"ca211e0ae0852f4f","network":"taboola","thumbnail":"/_img/taboola/ca211e0ae0852f4f","video_url":null,"title":"Easy Cruise Planning with Monthly EMIs [Book Now]","countries":["IN"],"last_seen":"2026-05-07T07:07:13+00:00"},{"id":"8f79747035ce84fd","network":"taboola","thumbnail":"/_img/taboola/8f79747035ce84fd","video_url":null,"title":"Plan Your Vacation to Lakshadweep with Cordelia Cruises","countries":["IN"],"last_seen":"2026-05-06T17:41:54+00:00"},{"id":"bf8195fa687a69ee","network":"taboola","thumbnail":"/_img/taboola/bf8195fa687a69ee","video_url":null,"title":"5-Night Malé & Colombo Cruise Starting ₹46,690","countries":["IN"],"last_seen":"2026-05-06T01:31:50+00:00"},{"id":"1dfd1b89717091cd","network":"taboola","thumbnail":"/_img/taboola/1dfd1b89717091cd","video_url":null,"title":"Malé & Colombo Cruise – Up to 26% Off","countries":["IN"],"last_seen":"2026-05-01T15:37:13+00:00"}]}