{"slug":"nissan","name":"Nissan","ad_count":39,"networks":["outbrain","taboola"],"countries":["DE","IT"],"verticals":["general"],"ads":[{"id":"fb7f76024dc94d28","network":"taboola","thumbnail":"/_img/taboola/fb7f76024dc94d28","video_url":null,"title":"Nissan QASHQAI: ricevi l’offerta pensata per te.","countries":["IT"],"last_seen":"2026-04-30T21:58:08+00:00"},{"id":"0d64b94cb460cdc0","network":"taboola","thumbnail":"/_img/taboola/0d64b94cb460cdc0","video_url":null,"title":"Nissan QASHQAI: ricevi l’offerta pensata per te.","countries":["IT"],"last_seen":"2026-04-29T21:26:20+00:00"},{"id":"e580776e40bc2a18","network":"taboola","thumbnail":"/_img/taboola/e580776e40bc2a18","video_url":null,"title":"Nuova Nissan MICRA. Diversa per scelta.","countries":["IT"],"last_seen":"2026-05-07T10:38:21+00:00"},{"id":"20f805ea9ac1c299","network":"outbrain","thumbnail":"/_img/outbrain/20f805ea9ac1c299","video_url":null,"title":"All eyes on MICRA: bring im Nissan MICRA deine Stadt zum Staunen.","countries":["DE"],"last_seen":"2026-05-07T10:55:23+00:00"},{"id":"e8954730d699c277","network":"outbrain","thumbnail":"/_img/outbrain/e8954730d699c277","video_url":null,"title":"Macht jeden Augenblick zum Blickfang: der neuen Nissan MICRA. 100% elektrisch.","countries":["DE"],"last_seen":"2026-05-07T10:49:25+00:00"},{"id":"16c3bb5b592cb432","network":"outbrain","thumbnail":"/_img/outbrain/16c3bb5b592cb432","video_url":null,"title":"Unterwegs Schulterblicke ernten: in die City im 100% elektrischen Nissan MICRA.","countries":["DE"],"last_seen":"2026-05-07T10:43:40+00:00"},{"id":"14220eb1b535b355","network":"outbrain","thumbnail":"/_img/outbrain/14220eb1b535b355","video_url":null,"title":"Unterwegs Schulterblicke ernten: in die City im 100% elektrischen Nissan MICRA.","countries":["DE"],"last_seen":"2026-05-07T10:21:15+00:00"},{"id":"982447cf2211654e","network":"outbrain","thumbnail":"/_img/outbrain/982447cf2211654e","video_url":null,"title":"Autofahrt wird zu Street Art: der neue Nissan MICRA. 100% elektrisch.","countries":["DE"],"last_seen":"2026-05-07T10:15:42+00:00"},{"id":"0a87ca7cb2007413","network":"outbrain","thumbnail":"/_img/outbrain/0a87ca7cb2007413","video_url":null,"title":"Unterwegs Schulterblicke ernten: in die City im 100% elektrischen Nissan MICRA.","countries":["DE"],"last_seen":"2026-05-07T09:59:24+00:00"},{"id":"673281300b01d20b","network":"outbrain","thumbnail":"/_img/outbrain/673281300b01d20b","video_url":null,"title":"Eine Urban Legend: werde zum talk of the town im 100% elektrischen Nissan MICRA.","countries":["DE"],"last_seen":"2026-05-07T09:31:01+00:00"},{"id":"b8cc9694e296b35a","network":"outbrain","thumbnail":"/_img/outbrain/b8cc9694e296b35a","video_url":null,"title":"Im Mittelpunkt des Stadtzentrums: der neue und 100% elektrische Nissan MICRA.","countries":["DE"],"last_seen":"2026-05-07T09:03:03+00:00"},{"id":"80b65290db382bb6","network":"outbrain","thumbnail":"/_img/outbrain/80b65290db382bb6","video_url":null,"title":"Im Mittelpunkt des Stadtzentrums: der neue und 100% elektrische Nissan MICRA.","countries":["DE"],"last_seen":"2026-05-07T07:10:13+00:00"},{"id":"fe8e005268bf1f28","network":"outbrain","thumbnail":"/_img/outbrain/fe8e005268bf1f28","video_url":null,"title":"Autofahrt wird zu Street Art: der neue Nissan MICRA. 100% elektrisch.","countries":["DE"],"last_seen":"2026-05-07T06:22:52+00:00"},{"id":"38d3d8e40296ec96","network":"outbrain","thumbnail":"/_img/outbrain/38d3d8e40296ec96","video_url":null,"title":"Unterwegs Schulterblicke ernten: in die City im 100% elektrischen Nissan MICRA.","countries":["DE"],"last_seen":"2026-05-07T06:06:44+00:00"},{"id":"f98dcdfc17ccfdf8","network":"outbrain","thumbnail":"/_img/outbrain/f98dcdfc17ccfdf8","video_url":null,"title":"Unterwegs Schulterblicke ernten: in die City im 100% elektrischen Nissan MICRA.","countries":["DE"],"last_seen":"2026-05-07T06:06:37+00:00"},{"id":"b54488c883c69379","network":"outbrain","thumbnail":"/_img/outbrain/b54488c883c69379","video_url":null,"title":"Eine Urban Legend: werde zum talk of the town im 100% elektrischen Nissan MICRA.","countries":["DE"],"last_seen":"2026-05-07T06:02:41+00:00"},{"id":"b3a4c7bda3b17851","network":"outbrain","thumbnail":"/_img/outbrain/b3a4c7bda3b17851","video_url":null,"title":"Mach die Stadtfahrt zum Stadtgespräch: der neue Nissan MICRA, 100% elektrisch.","countries":["DE"],"last_seen":"2026-05-07T05:41:16+00:00"},{"id":"306ca03269d9220c","network":"outbrain","thumbnail":"/_img/outbrain/306ca03269d9220c","video_url":null,"title":"Unterwegs Schulterblicke ernten: in die City im 100% elektrischen Nissan MICRA.","countries":["DE"],"last_seen":"2026-05-07T05:30:20+00:00"},{"id":"c285e4ecbf7c54bc","network":"outbrain","thumbnail":"/_img/outbrain/c285e4ecbf7c54bc","video_url":null,"title":"Mach die Stadtfahrt zum Stadtgespräch: der neue Nissan MICRA, 100% elektrisch.","countries":["DE"],"last_seen":"2026-05-07T04:42:56+00:00"},{"id":"3c28493154eb23b1","network":"outbrain","thumbnail":"/_img/outbrain/3c28493154eb23b1","video_url":null,"title":"Im Mittelpunkt des Stadtzentrums: der neue und 100% elektrische Nissan MICRA.","countries":["DE"],"last_seen":"2026-05-06T12:40:49+00:00"},{"id":"6cf1073ae447d88e","network":"outbrain","thumbnail":"/_img/outbrain/6cf1073ae447d88e","video_url":null,"title":"100% elektrisch und 100% elektrisierend: der neue Nissan MICRA.","countries":["DE"],"last_seen":"2026-05-06T12:17:01+00:00"},{"id":"2da0c1bd36f24469","network":"outbrain","thumbnail":"/_img/outbrain/2da0c1bd36f24469","video_url":null,"title":"Macht jeden Augenblick zum Blickfang: der neuen Nissan MICRA. 100% elektrisch.","countries":["DE"],"last_seen":"2026-05-06T11:46:43+00:00"},{"id":"7c6a5e5e5c106882","network":"outbrain","thumbnail":"/_img/outbrain/7c6a5e5e5c106882","video_url":null,"title":"All eyes on MICRA: bring im Nissan MICRA deine Stadt zum Staunen.","countries":["DE"],"last_seen":"2026-05-06T11:30:17+00:00"},{"id":"d75cc467de0cf3ec","network":"outbrain","thumbnail":"/_img/outbrain/d75cc467de0cf3ec","video_url":null,"title":"Macht jeden Augenblick zum Blickfang: der neuen Nissan MICRA. 100% elektrisch.","countries":["DE"],"last_seen":"2026-05-06T11:13:21+00:00"},{"id":"dcb00c77b41ee43c","network":"outbrain","thumbnail":"/_img/outbrain/dcb00c77b41ee43c","video_url":null,"title":"All eyes on MICRA: bring im Nissan MICRA deine Stadt zum Staunen.","countries":["DE"],"last_seen":"2026-05-06T10:17:28+00:00"},{"id":"08be3ed59d400089","network":"outbrain","thumbnail":"/_img/outbrain/08be3ed59d400089","video_url":null,"title":"Autofahrt wird zu Street Art: der neue Nissan MICRA. 100% elektrisch.","countries":["DE"],"last_seen":"2026-05-06T08:43:06+00:00"},{"id":"bff0c2915d13a6c7","network":"outbrain","thumbnail":"/_img/outbrain/bff0c2915d13a6c7","video_url":null,"title":"Mach die Stadtfahrt zum Stadtgespräch: der neue Nissan MICRA, 100% elektrisch.","countries":["DE"],"last_seen":"2026-05-06T08:31:29+00:00"},{"id":"7503cd6c0aa53263","network":"outbrain","thumbnail":"/_img/outbrain/7503cd6c0aa53263","video_url":null,"title":"100% elektrisch und 100% elektrisierend: der neue Nissan MICRA.","countries":["DE"],"last_seen":"2026-05-06T08:19:21+00:00"},{"id":"f1491ba566322f40","network":"outbrain","thumbnail":"/_img/outbrain/f1491ba566322f40","video_url":null,"title":"Im Mittelpunkt des Stadtzentrums: der neue und 100% elektrische Nissan MICRA.","countries":["DE"],"last_seen":"2026-05-06T07:38:19+00:00"},{"id":"4f9b8032e8202615","network":"outbrain","thumbnail":"/_img/outbrain/4f9b8032e8202615","video_url":null,"title":"Macht jeden Augenblick zum Blickfang: der neuen Nissan MICRA. 100% elektrisch.","countries":["DE"],"last_seen":"2026-05-06T07:33:08+00:00"},{"id":"8da42d9cb3c87e22","network":"outbrain","thumbnail":"/_img/outbrain/8da42d9cb3c87e22","video_url":null,"title":"Im Mittelpunkt des Stadtzentrums: der neue und 100% elektrische Nissan MICRA.","countries":["DE"],"last_seen":"2026-05-06T04:19:07+00:00"},{"id":"a375d303d9eacef2","network":"outbrain","thumbnail":"/_img/outbrain/a375d303d9eacef2","video_url":null,"title":"100% elektrisch und 100% elektrisierend: der neue Nissan MICRA.","countries":["DE"],"last_seen":"2026-05-04T08:30:45+00:00"},{"id":"a7242df3ef111010","network":"outbrain","thumbnail":"/_img/outbrain/a7242df3ef111010","video_url":null,"title":"Mach die Stadtfahrt zum Stadtgespräch: der neue Nissan MICRA, 100% elektrisch.","countries":["DE"],"last_seen":"2026-05-04T08:11:24+00:00"},{"id":"e7849275a9419f9b","network":"outbrain","thumbnail":"/_img/outbrain/e7849275a9419f9b","video_url":null,"title":"Macht jeden Augenblick zum Blickfang: der neuen Nissan MICRA. 100% elektrisch.","countries":["DE"],"last_seen":"2026-05-04T06:26:44+00:00"},{"id":"4e5fb1fee4030ad2","network":"outbrain","thumbnail":"/_img/outbrain/4e5fb1fee4030ad2","video_url":null,"title":"Autofahrt wird zu Street Art: der neue Nissan MICRA. 100% elektrisch.","countries":["DE"],"last_seen":"2026-05-04T06:15:37+00:00"},{"id":"f4b80f81dd4e4444","network":"outbrain","thumbnail":"/_img/outbrain/f4b80f81dd4e4444","video_url":null,"title":"Im Mittelpunkt des Stadtzentrums: der neue und 100% elektrische Nissan MICRA.","countries":["DE"],"last_seen":"2026-05-03T18:37:09+00:00"},{"id":"eeda8b9ce5509488","network":"outbrain","thumbnail":"/_img/outbrain/eeda8b9ce5509488","video_url":null,"title":"Macht jeden Augenblick zum Blickfang: der neuen Nissan MICRA. 100% elektrisch.","countries":["DE"],"last_seen":"2026-05-03T13:58:38+00:00"},{"id":"94095b6af2aee556","network":"outbrain","thumbnail":"/_img/outbrain/94095b6af2aee556","video_url":null,"title":"Mach die Stadtfahrt zum Stadtgespräch: der neue Nissan MICRA, 100% elektrisch.","countries":["DE"],"last_seen":"2026-05-03T07:00:28+00:00"},{"id":"6dd43ca31071561b","network":"outbrain","thumbnail":"/_img/outbrain/6dd43ca31071561b","video_url":null,"title":"All eyes on MICRA: bring im Nissan MICRA deine Stadt zum Staunen.","countries":["DE"],"last_seen":"2026-05-03T05:17:35+00:00"}]}