{"slug":"rubaxx-cbd-plus","name":"Rubaxx CBD Plus","ad_count":4,"networks":["taboola"],"countries":["DE"],"verticals":["health"],"ads":[{"id":"4dc304beb9776b97","network":"taboola","thumbnail":"/_img/taboola/4dc304beb9776b97","video_url":null,"title":"Testsieger bei Schmerz- und Muskelgelen 2026: Das neue Kraft-Upgrade aus der Apotheke","countries":["DE"],"last_seen":"2026-05-07T09:54:56+00:00"},{"id":"3e01b23afe8a42d7","network":"taboola","thumbnail":"/_img/taboola/3e01b23afe8a42d7","video_url":null,"title":"Schmerz- und Muskelgele 2026: Das neue Kraft-Upgrade aus der Apotheke ist da!","countries":["DE"],"last_seen":"2026-05-07T09:38:40+00:00"},{"id":"d9682cac6c51c06b","network":"taboola","thumbnail":"/_img/taboola/d9682cac6c51c06b","video_url":null,"title":"Testsieger bei Schmerz- und Muskelgelen 2026: Das neue Kraft-Upgrade aus der Apotheke","countries":["DE"],"last_seen":"2026-05-07T04:04:07+00:00"},{"id":"bb5a712fc3b0adf0","network":"taboola","thumbnail":"/_img/taboola/bb5a712fc3b0adf0","video_url":null,"title":"NEUES Gel mit über 1000mg CBD aktiviert die Haut und entspannt beanspruchte Muskeln","countries":["DE"],"last_seen":"2026-05-02T04:17:08+00:00"}]}