{"slug":"rv-camper-motorhomes","name":"RV, Camper & Motorhomes","ad_count":10,"networks":["taboola"],"countries":["AT","AU","BE","BG","BR","CA","CH","CL","CZ","DK","ES","FI","FR","GB","GR","HU","IE","IL","IT","JP"],"verticals":["auto"],"ads":[{"id":"99c45e78cf4f4dff","network":"taboola","thumbnail":"/_img/taboola/99c45e78cf4f4dff","video_url":null,"title":"These Are the Current Prices for Small RVs & Camper Vans For Pensioners","countries":["AT","AU","BE","BG","BR","CA","CH","CL","CZ","DK","ES","FI","FR","GB","GR","HU","IE","IL","IT","MX","NL","NO","NZ","PL","PT","QA","RO","SE","SG","SK","TH","TR"],"last_seen":"2026-05-07T10:30:29+00:00"},{"id":"fce9e5e70d21fcd5","network":"taboola","thumbnail":"/_img/taboola/fce9e5e70d21fcd5","video_url":null,"title":"These Are the Current Prices for Small RVs & Camper Vans For Pensioners","countries":["AU","BE","BG","BR","CA","CL","CZ","DK","ES","FI","FR","GB","GR","HU","IE","IT","MX","NL","NO","NZ","PL","PT","QA","RO","SE","SG","SK","TH","TR"],"last_seen":"2026-05-07T10:29:38+00:00"},{"id":"771b34c8c9e4ce01","network":"taboola","thumbnail":"/_img/taboola/771b34c8c9e4ce01","video_url":null,"title":"Here Is Why 2-Berth Camper Vans Often Chosen By Pensioners","countries":["AT","AU","BE","BG","BR","CA","CH","CL","CZ","DK","ES","FI","FR","GB","GR","HU","IE","IL","IT","MX","NL","NO","NZ","PL","PT","QA","RO","SE","SG","SK","TH","TR"],"last_seen":"2026-05-07T10:29:38+00:00"},{"id":"e73cf2c3f4dfc1bf","network":"taboola","thumbnail":"/_img/taboola/e73cf2c3f4dfc1bf","video_url":null,"title":"Why 2-Berth Camper Vans Suit Pensioners","countries":["AT","AU","BE","BG","BR","CA","CH","CL","CZ","DK","ES","FI","FR","GB","GR","HU","IE","IL","IT","MX","NL","NO","NZ","PL","PT","QA","RO","SE","SG","SK","TH","TR"],"last_seen":"2026-05-07T10:29:05+00:00"},{"id":"59b8abf4c0560eae","network":"taboola","thumbnail":"/_img/taboola/59b8abf4c0560eae","video_url":null,"title":"Here Is Why 2-Berth Camper Vans Often Chosen By Pensioners","countries":["BE","BG","BR","CL","CZ","DK","FI","HU","IE","MX","NO","PL","QA","RO","SK","TH"],"last_seen":"2026-05-07T10:29:05+00:00"},{"id":"9d4463f4603309ec","network":"taboola","thumbnail":"/_img/taboola/9d4463f4603309ec","video_url":null,"title":"Why 2-Berth Camper Vans Suit Pensioners","countries":["AT","AU","BE","BG","BR","CA","CH","CL","CZ","DK","ES","FI","GB","GR","HU","IE","IL","IT","MX","NL","NO","NZ","PL","PT","QA","RO","SE","SG","SK","TH","TR","US"],"last_seen":"2026-05-07T10:11:14+00:00"},{"id":"548ce8ae612fea82","network":"taboola","thumbnail":"/_img/taboola/548ce8ae612fea82","video_url":null,"title":"These Are the Current Prices for Small RVs & Camper Vans For Pensioners","countries":["AT","AU","BE","BG","BR","CA","CH","CL","CZ","DK","ES","FI","FR","GB","GR","HU","IE","IL","IT","MX","NL","NO","NZ","PL","PT","QA","RO","SE","SG","SK","TH","TR"],"last_seen":"2026-04-25T00:31:29+00:00"},{"id":"f4caa060f17826ed","network":"taboola","thumbnail":"/_img/taboola/f4caa060f17826ed","video_url":null,"title":"Here Is Why 2-Berth Camper Vans Often Chosen By Pensioners","countries":["AT","AU","BE","BG","BR","CA","CH","CL","CZ","DK","ES","FI","GB","GR","HU","IE","IL","IT","MX","NL","NO","NZ","PL","PT","QA","RO","SE","SG","SK","TH","US"],"last_seen":"2026-04-25T00:26:53+00:00"},{"id":"4fc47fda0b70aa41","network":"taboola","thumbnail":"/_img/taboola/4fc47fda0b70aa41","video_url":null,"title":"Current Small RV And Camper Van Prices For Pensioners","countries":["AU","BE","BR","CA","CL","CZ","ES","FI","GB","IE","JP","MX","NL","SG","SK","TH","US"],"last_seen":"2026-05-07T10:45:39+00:00"},{"id":"465032cd74dbd005","network":"taboola","thumbnail":"/_img/taboola/465032cd74dbd005","video_url":null,"title":"These Are the Current Prices for Small RVs & Camper Vans For Pensioners","countries":["BE","BG","BR","CL","CZ","DK","FI","GR","HU","IE","IT","NL","NO","PL","QA","RO","SK","TR"],"last_seen":"2026-05-07T10:12:46+00:00"}]}