{"slug":"shellsen-com","name":"Shellsen.com","ad_count":5,"networks":["taboola"],"countries":["CZ"],"verticals":["general"],"ads":[{"id":"0fb7e202b0de92df","network":"taboola","thumbnail":"/_img/taboola/0fb7e202b0de92df","video_url":null,"title":"Perfektní boty pro celodenní chůzi a stání","countries":["CZ"],"last_seen":"2026-05-07T10:31:02+00:00"},{"id":"6842215cb7b9d501","network":"taboola","thumbnail":"/_img/taboola/6842215cb7b9d501","video_url":null,"title":"Tajemství pohodlné chůze se skrývá v těchto barefoot botách.","countries":["CZ"],"last_seen":"2026-05-07T08:37:19+00:00"},{"id":"b0698bb2d844d64e","network":"taboola","thumbnail":"/_img/taboola/b0698bb2d844d64e","video_url":null,"title":"Perfektní boty pro celodenní chůzi a stání","countries":["CZ"],"last_seen":"2026-04-21T11:48:54+00:00"},{"id":"b08a200db27bca4e","network":"taboola","thumbnail":"/_img/taboola/b08a200db27bca4e","video_url":null,"title":"Obujte si je a naplno si užijte každou cestu.","countries":["CZ"],"last_seen":"2026-04-21T11:48:54+00:00"},{"id":"68a72e33146877e6","network":"taboola","thumbnail":"/_img/taboola/68a72e33146877e6","video_url":null,"title":"Dokonalá obuv pro celodenní chůzi a stání.","countries":["CZ"],"last_seen":"2026-05-07T10:39:23+00:00"}]}