{"slug":"verisure","name":"Verisure®","ad_count":17,"networks":["outbrain","taboola"],"countries":["CL","FR","NL"],"verticals":["general","tech"],"ads":[{"id":"7f5ff4902339db1f","network":"taboola","thumbnail":"/_img/taboola/7f5ff4902339db1f","video_url":null,"title":"Tijdelijke videodeurbel aanbieding met 24/7 alarmsysteem","countries":["NL"],"last_seen":"2026-05-07T10:59:42+00:00"},{"id":"63f2bae4b2fa59b5","network":"taboola","thumbnail":"/_img/taboola/63f2bae4b2fa59b5","video_url":null,"title":"Deze videodeurbel is dе hit vаn 2026","countries":["NL"],"last_seen":"2026-05-07T10:57:08+00:00"},{"id":"d21ec606e48f904b","network":"taboola","thumbnail":"/_img/taboola/d21ec606e48f904b","video_url":null,"title":"Tijdelijke videodeurbel aanbieding met 24/7 alarmsysteem","countries":["NL"],"last_seen":"2026-05-07T10:47:55+00:00"},{"id":"f18d06e813bfbed2","network":"taboola","thumbnail":"/_img/taboola/f18d06e813bfbed2","video_url":null,"title":"Ben je op zoek naar een alarmsysteem met videodeurbel?","countries":["NL"],"last_seen":"2026-05-07T10:47:55+00:00"},{"id":"6081e951324d7449","network":"taboola","thumbnail":"/_img/taboola/6081e951324d7449","video_url":null,"title":"Sécurité de votre maison : combien ça coûte vraiment ?","countries":["FR"],"last_seen":"2026-05-07T10:45:35+00:00"},{"id":"365e17b5c8957b1e","network":"taboola","thumbnail":"/_img/taboola/365e17b5c8957b1e","video_url":null,"title":"Professioneel 24/7 alarmsysteem met videodeurbel","countries":["NL"],"last_seen":"2026-05-07T10:45:20+00:00"},{"id":"ceece4b6d6204043","network":"taboola","thumbnail":"/_img/taboola/ceece4b6d6204043","video_url":null,"title":"Professioneel 24/7 alarmsysteem met videodeurbel","countries":["NL"],"last_seen":"2026-05-07T10:44:04+00:00"},{"id":"3859053118eb4b5d","network":"taboola","thumbnail":"/_img/taboola/3859053118eb4b5d","video_url":null,"title":"Combien coûte une alarme pour protéger efficacement votre maison ?","countries":["FR"],"last_seen":"2026-05-07T10:40:16+00:00"},{"id":"590e7c4b8cddebe7","network":"taboola","thumbnail":"/_img/taboola/590e7c4b8cddebe7","video_url":null,"title":"Une solution de sécurité accessible dès 199€ HT","countries":["FR"],"last_seen":"2026-05-07T10:05:11+00:00"},{"id":"8a0a4e8ef1ee5d71","network":"taboola","thumbnail":"/_img/taboola/8a0a4e8ef1ee5d71","video_url":null,"title":"Sécurité de votre maison : combien ça coûte vraiment ?","countries":["FR"],"last_seen":"2026-05-07T09:57:29+00:00"},{"id":"ec2a54830faa5ab9","network":"taboola","thumbnail":"/_img/taboola/ec2a54830faa5ab9","video_url":null,"title":"Combien coûte une alarme pour protéger efficacement votre maison ?","countries":["FR"],"last_seen":"2026-05-07T07:30:23+00:00"},{"id":"5f025a8ce7b36e1d","network":"taboola","thumbnail":"/_img/taboola/5f025a8ce7b36e1d","video_url":null,"title":"Ce que coûte réellement une alarme peut surprendre","countries":["FR"],"last_seen":"2026-05-06T05:45:39+00:00"},{"id":"2878277b57343c3e","network":"taboola","thumbnail":"/_img/taboola/2878277b57343c3e","video_url":null,"title":"¡Oferta exclusiva: Kit alarma con cámara Wi-Fi e inalámbrica! (ver precio)","countries":["CL"],"last_seen":"2026-05-04T08:37:24+00:00"},{"id":"6a2ade0f0af2a679","network":"taboola","thumbnail":"/_img/taboola/6a2ade0f0af2a679","video_url":null,"title":"¡Kit alarma con cámara Wi-Fi: ¡Precio increíble por tiempo limitado!","countries":["CL"],"last_seen":"2026-05-04T06:51:33+00:00"},{"id":"2052d27d531f85b0","network":"taboola","thumbnail":"/_img/taboola/2052d27d531f85b0","video_url":null,"title":"¡Kit alarma con cámara Wi-Fi: ¡Precio increíble por tiempo limitado!","countries":["CL"],"last_seen":"2026-05-04T06:49:42+00:00"},{"id":"86dbd70c28d5395b","network":"taboola","thumbnail":"/_img/taboola/86dbd70c28d5395b","video_url":null,"title":"¡Oferta exclusiva: Kit alarma con cámara Wi-Fi e inalámbrica! (ver precio)","countries":["CL"],"last_seen":"2026-05-04T06:46:54+00:00"},{"id":"77225c2de4750a8d","network":"outbrain","thumbnail":"/_img/outbrain/77225c2de4750a8d","video_url":null,"title":"Ce que coûte réellement une alarme peut surprendre","countries":["FR"],"last_seen":"2026-05-07T08:10:40+00:00"}]}